{ "height":25,
 "layers":[
        {
         "draworder":"topdown",
         "height":0,
         "name":"scene_race",
         "objects":[],
         "opacity":1,
         "properties":
            {
             "#tile":"tile_race",
             "backgroundTileX":"16",
             "set":"{\"_\":[\"stencil\",\"stageModel\"]}",
             "shadowX":"0",
             "shadowY":"0",
             "skaneSpeed":"1",
             "snakeTileY":"32",
             "stageComment":"\"3 laps to go!\"",
             "stageName":"\"Race\"",
             "startX":"28",
             "startY":"15",
             "states":"{\n        \"name\":\"game\",\n        \"like\":{\"_\":[\"stencil\",\"modelRace\"]}\n      }",
             "targetLength":"20"
            },
         "type":"objectgroup",
         "visible":false,
         "width":0,
         "x":0,
         "y":0
        }, 
        {
         "data":[0, 0, 0, 0, 0, 0, 0, 0, 0, 0, 0, 0, 0, 0, 0, 0, 0, 0, 0, 0, 0, 0, 0, 0, 0, 0, 0, 0, 0, 0, 0, 0, 0, 0, 0, 0, 0, 0, 0, 0, 0, 0, 184, 184, 184, 184, 0, 0, 0, 0, 0, 0, 0, 0, 0, 0, 0, 0, 184, 166, 166, 184, 0, 186, 186, 186, 186, 186, 186, 186, 186, 186, 186, 186, 186, 186, 186, 186, 186, 0, 186, 169, 170, 170, 170, 170, 170, 170, 170, 170, 170, 170, 170, 170, 170, 170, 170, 171, 184, 184, 184, 184, 0, 0, 167, 167, 167, 169, 170, 170, 170, 170, 170, 170, 170, 170, 170, 170, 171, 0, 186, 168, 0, 0, 0, 0, 0, 0, 0, 0, 0, 0, 0, 0, 0, 0, 0, 172, 167, 167, 167, 167, 167, 0, 163, 163, 163, 172, 0, 0, 0, 0, 0, 0, 0, 0, 0, 0, 172, 0, 186, 168, 0, 0, 0, 0, 0, 0, 0, 0, 0, 0, 0, 0, 0, 0, 0, 172, 163, 163, 163, 163, 163, 0, 184, 166, 184, 172, 0, 0, 0, 0, 0, 0, 0, 0, 0, 0, 172, 167, 167, 168, 0, 0, 0, 0, 0, 0, 0, 0, 0, 0, 0, 0, 0, 0, 0, 172, 162, 166, 162, 166, 162, 0, 184, 184, 184, 172, 0, 0, 0, 0, 0, 0, 0, 0, 0, 0, 172, 163, 163, 168, 0, 0, 0, 0, 0, 0, 0, 0, 0, 0, 0, 0, 0, 0, 0, 172, 162, 162, 162, 162, 162, 0, 0, 0, 0, 172, 0, 0, 0, 0, 0, 0, 0, 0, 0, 0, 172, 162, 184, 168, 0, 0, 0, 0, 169, 170, 170, 170, 170, 170, 171, 0, 0, 0, 0, 175, 174, 174, 174, 174, 174, 174, 174, 174, 174, 173, 0, 0, 0, 0, 169, 171, 0, 0, 0, 0, 172, 162, 167, 168, 0, 0, 0, 0, 168, 167, 167, 167, 167, 167, 172, 0, 0, 0, 0, 0, 0, 0, 0, 0, 0, 0, 0, 0, 0, 0, 0, 0, 0, 0, 172, 168, 0, 0, 0, 0, 172, 0, 163, 168, 0, 0, 0, 0, 168, 163, 163, 163, 163, 163, 172, 0, 0, 0, 0, 0, 0, 0, 0, 0, 0, 0, 0, 0, 0, 0, 0, 0, 0, 0, 172, 168, 0, 0, 0, 0, 172, 0, 184, 168, 0, 0, 0, 0, 168, 165, 166, 165, 166, 165, 172, 0, 0, 0, 0, 0, 0, 0, 0, 0, 0, 0, 0, 0, 0, 0, 0, 0, 0, 0, 172, 168, 0, 0, 0, 0, 172, 0, 184, 168, 0, 0, 0, 0, 168, 165, 165, 165, 165, 165, 172, 0, 0, 0, 0, 0, 0, 0, 0, 0, 0, 0, 0, 0, 0, 0, 0, 0, 0, 0, 172, 168, 0, 0, 0, 0, 172, 0, 0, 168, 0, 0, 0, 0, 168, 0, 0, 0, 0, 0, 175, 174, 174, 174, 174, 174, 174, 174, 174, 174, 174, 174, 174, 174, 174, 174, 174, 174, 174, 174, 173, 168, 0, 0, 0, 0, 172, 0, 0, 168, 0, 0, 0, 0, 168, 167, 167, 167, 167, 167, 169, 170, 170, 170, 170, 170, 170, 170, 170, 170, 170, 170, 170, 170, 170, 170, 170, 170, 170, 170, 171, 168, 0, 0, 0, 0, 172, 0, 0, 168, 0, 0, 0, 0, 168, 163, 163, 163, 163, 163, 172, 0, 0, 0, 0, 0, 0, 185, 0, 0, 0, 0, 0, 0, 0, 0, 0, 0, 0, 0, 172, 168, 0, 0, 0, 0, 172, 0, 0, 168, 0, 0, 0, 0, 168, 162, 166, 162, 166, 162, 172, 0, 0, 0, 0, 0, 0, 185, 0, 0, 0, 0, 0, 0, 0, 0, 0, 0, 0, 0, 172, 168, 0, 0, 0, 0, 172, 0, 167, 168, 0, 0, 0, 0, 168, 162, 162, 162, 162, 162, 172, 0, 0, 0, 0, 0, 0, 185, 0, 0, 0, 0, 0, 0, 0, 0, 0, 0, 0, 0, 172, 168, 0, 0, 0, 0, 172, 186, 163, 168, 0, 0, 0, 0, 175, 174, 174, 174, 174, 174, 173, 0, 0, 0, 0, 0, 0, 185, 0, 0, 0, 0, 0, 0, 0, 0, 0, 0, 0, 0, 175, 173, 0, 0, 0, 0, 172, 186, 162, 168, 0, 0, 0, 0, 0, 0, 0, 0, 0, 0, 0, 0, 0, 0, 0, 169, 170, 170, 170, 170, 170, 170, 170, 170, 170, 171, 0, 0, 0, 0, 0, 0, 0, 0, 0, 0, 172, 186, 162, 168, 0, 0, 0, 0, 0, 0, 0, 0, 0, 0, 0, 0, 0, 0, 0, 168, 186, 186, 186, 186, 186, 186, 186, 186, 186, 172, 0, 0, 0, 0, 0, 0, 0, 0, 0, 0, 172, 186, 0, 168, 0, 0, 0, 0, 0, 0, 0, 0, 0, 0, 0, 0, 0, 0, 0, 168, 186, 176, 176, 176, 176, 176, 176, 176, 186, 172, 0, 0, 0, 0, 0, 0, 0, 0, 0, 0, 172, 186, 0, 168, 0, 0, 0, 0, 0, 0, 0, 0, 0, 0, 0, 0, 0, 0, 0, 168, 167, 167, 167, 167, 167, 176, 176, 176, 186, 172, 0, 0, 0, 0, 0, 0, 0, 0, 0, 0, 172, 186, 0, 175, 174, 174, 174, 174, 174, 174, 174, 174, 174, 174, 174, 174, 174, 174, 174, 173, 163, 163, 163, 163, 163, 0, 0, 0, 186, 175, 174, 174, 174, 174, 174, 174, 174, 174, 174, 174, 173, 186, 0, 186, 186, 186, 186, 186, 186, 186, 186, 186, 186, 186, 186, 186, 186, 186, 186, 186, 162, 166, 162, 166, 162, 0, 0, 0, 186, 186, 186, 186, 186, 186, 186, 186, 186, 186, 186, 186, 186, 186, 0, 0, 0, 0, 0, 0, 0, 0, 0, 0, 0, 0, 0, 0, 0, 0, 0, 0, 0, 0, 0, 0, 0, 0, 0, 0, 0, 0, 0, 0, 0, 0, 0, 0, 0, 0, 0, 0, 0, 0],
         "height":25,
         "name":"tile_race",
         "opacity":1,
         "type":"tilelayer",
         "visible":false,
         "width":40,
         "x":0,
         "y":0
        }, 
        {
         "draworder":"topdown",
         "height":0,
         "name":"scene_sides",
         "objects":[],
         "opacity":1,
         "properties":
            {
             "#tile":"tile_sides",
             "backgroundTileX":"8",
             "backgroundTileY":"8",
             "set":"{\"_\":[\"stencil\",\"stageModel\"]}",
             "shadowX":"0",
             "shadowY":"0",
             "snakeTileY":"24",
             "stageComment":"\"One way!\"",
             "stageName":"\"Sides\"",
             "states":"{\n        \"name\":\"game\",\n        \"like\":[{\"_\":[\"stencil\",\"modelFoodKeeper\"]},{\"_\":[\"stencil\",\"modelSides\"]}]\n      }"
            },
         "type":"objectgroup",
         "visible":false,
         "width":0,
         "x":0,
         "y":0
        }, 
        {
         "data":[0, 0, 0, 0, 0, 0, 0, 0, 0, 0, 0, 0, 0, 0, 0, 0, 0, 0, 0, 0, 0, 0, 0, 0, 0, 0, 0, 0, 0, 0, 0, 0, 0, 0, 0, 0, 0, 0, 0, 0, 184, 184, 184, 184, 184, 184, 184, 184, 184, 184, 184, 184, 184, 184, 184, 184, 184, 184, 184, 184, 184, 184, 184, 184, 184, 184, 184, 184, 184, 184, 184, 184, 184, 184, 184, 184, 184, 184, 184, 184, 184, 0, 0, 0, 0, 0, 0, 0, 0, 0, 0, 0, 182, 0, 0, 0, 0, 0, 0, 0, 0, 0, 0, 0, 0, 0, 0, 182, 0, 0, 0, 0, 0, 0, 0, 0, 0, 0, 0, 184, 184, 0, 0, 0, 0, 0, 0, 0, 0, 0, 0, 0, 182, 0, 0, 0, 0, 0, 0, 0, 0, 0, 0, 0, 0, 0, 0, 182, 0, 0, 0, 0, 0, 0, 0, 0, 0, 0, 0, 184, 184, 0, 0, 0, 0, 0, 0, 0, 0, 0, 0, 0, 182, 0, 0, 0, 0, 0, 0, 0, 0, 0, 0, 0, 0, 0, 0, 182, 0, 0, 0, 0, 0, 0, 0, 0, 0, 0, 0, 184, 184, 0, 0, 0, 0, 0, 0, 0, 0, 0, 0, 0, 182, 0, 0, 0, 0, 0, 0, 0, 0, 0, 0, 0, 0, 0, 0, 182, 0, 0, 0, 0, 0, 0, 0, 0, 0, 0, 0, 184, 184, 0, 0, 0, 0, 0, 0, 0, 0, 0, 0, 0, 182, 0, 0, 0, 0, 0, 0, 0, 0, 0, 0, 0, 0, 0, 0, 182, 0, 0, 0, 0, 0, 0, 0, 0, 0, 0, 0, 184, 184, 0, 0, 0, 0, 0, 0, 0, 0, 0, 0, 0, 182, 0, 0, 0, 0, 0, 0, 0, 0, 0, 0, 0, 0, 0, 0, 182, 0, 0, 0, 0, 0, 0, 0, 0, 0, 0, 0, 184, 184, 0, 0, 0, 0, 0, 0, 0, 0, 0, 0, 0, 182, 0, 0, 0, 0, 0, 0, 0, 0, 0, 0, 0, 0, 0, 0, 182, 0, 0, 0, 0, 0, 0, 0, 0, 0, 0, 0, 184, 184, 0, 0, 0, 0, 0, 0, 0, 0, 0, 0, 0, 182, 0, 0, 0, 0, 0, 0, 0, 0, 0, 0, 0, 0, 0, 0, 182, 0, 0, 0, 0, 0, 0, 0, 0, 0, 0, 0, 184, 184, 0, 0, 0, 0, 0, 0, 0, 0, 0, 0, 0, 184, 180, 180, 180, 180, 180, 180, 180, 180, 180, 180, 180, 180, 180, 180, 184, 0, 0, 0, 0, 0, 0, 0, 0, 0, 0, 0, 184, 184, 0, 0, 0, 0, 0, 0, 0, 0, 0, 0, 0, 0, 0, 0, 0, 0, 0, 0, 0, 0, 0, 0, 0, 0, 0, 0, 0, 0, 0, 0, 0, 0, 0, 0, 0, 0, 0, 0, 184, 184, 0, 0, 0, 0, 0, 0, 0, 0, 0, 0, 0, 0, 0, 0, 0, 0, 0, 0, 0, 0, 0, 0, 0, 0, 0, 0, 0, 0, 0, 0, 0, 0, 0, 0, 0, 0, 0, 0, 184, 184, 0, 0, 0, 0, 0, 0, 0, 0, 0, 0, 0, 0, 0, 0, 0, 0, 0, 0, 0, 0, 0, 0, 0, 0, 0, 0, 0, 0, 0, 0, 0, 0, 0, 0, 0, 0, 0, 0, 184, 184, 0, 0, 0, 0, 0, 0, 0, 0, 0, 0, 0, 184, 181, 181, 181, 181, 181, 181, 181, 181, 181, 181, 181, 181, 181, 181, 184, 0, 0, 0, 0, 0, 0, 0, 0, 0, 0, 0, 184, 184, 0, 0, 0, 0, 0, 0, 0, 0, 0, 0, 0, 183, 0, 0, 0, 0, 0, 0, 0, 0, 0, 0, 0, 0, 0, 0, 183, 0, 0, 0, 0, 0, 0, 0, 0, 0, 0, 0, 184, 184, 0, 0, 0, 0, 0, 0, 0, 0, 0, 0, 0, 183, 0, 0, 0, 0, 0, 0, 0, 0, 0, 0, 0, 0, 0, 0, 183, 0, 0, 0, 0, 0, 0, 0, 0, 0, 0, 0, 184, 184, 0, 0, 0, 0, 0, 0, 0, 0, 0, 0, 0, 183, 0, 0, 0, 0, 0, 0, 0, 0, 0, 0, 0, 0, 0, 0, 183, 0, 0, 0, 0, 0, 0, 0, 0, 0, 0, 0, 184, 184, 0, 0, 0, 0, 0, 0, 0, 0, 0, 0, 0, 183, 0, 0, 0, 0, 0, 0, 0, 0, 0, 0, 0, 0, 0, 0, 183, 0, 0, 0, 0, 0, 0, 0, 0, 0, 0, 0, 184, 184, 0, 0, 0, 0, 0, 0, 0, 0, 0, 0, 0, 183, 0, 0, 0, 0, 0, 0, 0, 0, 0, 0, 0, 0, 0, 0, 183, 0, 0, 0, 0, 0, 0, 0, 0, 0, 0, 0, 184, 184, 0, 0, 0, 0, 0, 0, 0, 0, 0, 0, 0, 183, 0, 0, 0, 0, 0, 0, 0, 0, 0, 0, 0, 0, 0, 0, 183, 0, 0, 0, 0, 0, 0, 0, 0, 0, 0, 0, 184, 184, 0, 0, 0, 0, 0, 0, 0, 0, 0, 0, 0, 183, 0, 0, 0, 0, 0, 0, 0, 0, 0, 0, 0, 0, 0, 0, 183, 0, 0, 0, 0, 0, 0, 0, 0, 0, 0, 0, 184, 184, 0, 0, 0, 0, 0, 0, 0, 0, 0, 0, 0, 183, 0, 0, 0, 0, 0, 0, 0, 0, 0, 0, 0, 0, 0, 0, 183, 0, 0, 0, 0, 0, 0, 0, 0, 0, 0, 0, 184, 184, 184, 184, 184, 184, 184, 184, 184, 184, 184, 184, 184, 184, 184, 184, 184, 184, 184, 184, 184, 184, 184, 184, 184, 184, 184, 184, 184, 184, 184, 184, 184, 184, 184, 184, 184, 184, 184, 184, 184, 0, 0, 0, 0, 0, 0, 0, 0, 0, 0, 0, 0, 0, 0, 0, 0, 0, 0, 0, 0, 0, 0, 0, 0, 0, 0, 0, 0, 0, 0, 0, 0, 0, 0, 0, 0, 0, 0, 0, 0],
         "height":25,
         "name":"tile_sides",
         "opacity":1,
         "type":"tilelayer",
         "visible":false,
         "width":40,
         "x":0,
         "y":0
        }, 
        {
         "data":[0, 0, 0, 0, 0, 0, 0, 0, 0, 0, 0, 0, 0, 0, 0, 0, 0, 0, 0, 0, 0, 0, 0, 0, 0, 0, 0, 0, 0, 0, 0, 0, 0, 0, 0, 0, 0, 0, 0, 0, 161, 161, 161, 161, 161, 161, 161, 161, 161, 161, 161, 161, 161, 161, 161, 161, 161, 161, 161, 161, 161, 161, 161, 161, 161, 161, 161, 161, 161, 161, 161, 161, 161, 161, 161, 161, 161, 161, 161, 161, 161, 0, 0, 0, 0, 0, 0, 0, 0, 0, 0, 161, 0, 0, 0, 0, 0, 0, 0, 0, 0, 0, 0, 0, 0, 0, 0, 0, 163, 0, 0, 0, 0, 0, 0, 0, 0, 0, 0, 161, 161, 0, 176, 0, 0, 0, 0, 0, 0, 178, 0, 161, 0, 178, 0, 0, 0, 0, 0, 0, 0, 0, 0, 0, 0, 0, 0, 0, 163, 0, 178, 0, 0, 0, 0, 0, 0, 176, 0, 161, 161, 0, 0, 0, 0, 0, 0, 0, 0, 0, 0, 161, 0, 0, 0, 0, 0, 0, 0, 0, 0, 0, 0, 0, 0, 0, 0, 0, 163, 0, 0, 0, 0, 0, 0, 0, 0, 0, 0, 161, 161, 0, 0, 0, 0, 0, 0, 0, 0, 0, 0, 161, 0, 0, 0, 0, 0, 0, 0, 0, 0, 0, 0, 0, 0, 0, 0, 0, 163, 0, 0, 0, 0, 0, 0, 0, 0, 0, 0, 161, 161, 0, 0, 0, 0, 0, 0, 0, 0, 0, 0, 161, 0, 0, 0, 0, 0, 0, 0, 0, 0, 0, 0, 0, 0, 0, 0, 0, 163, 0, 0, 0, 0, 0, 0, 0, 0, 0, 0, 161, 161, 0, 0, 0, 0, 0, 0, 0, 0, 0, 0, 161, 0, 0, 0, 0, 0, 0, 0, 0, 0, 0, 0, 0, 0, 0, 0, 0, 163, 0, 0, 0, 0, 0, 0, 0, 0, 0, 0, 161, 161, 0, 0, 0, 0, 0, 0, 0, 0, 0, 0, 161, 0, 0, 0, 0, 0, 0, 0, 0, 0, 0, 0, 0, 0, 0, 0, 0, 163, 0, 0, 0, 0, 0, 0, 0, 0, 0, 0, 161, 161, 0, 0, 0, 0, 0, 0, 0, 0, 177, 0, 161, 0, 0, 0, 0, 0, 0, 0, 0, 0, 0, 0, 0, 0, 0, 0, 0, 163, 0, 0, 0, 0, 0, 0, 0, 0, 0, 0, 161, 161, 0, 0, 0, 0, 0, 0, 0, 0, 0, 0, 161, 0, 0, 0, 0, 0, 0, 0, 0, 0, 0, 0, 0, 0, 0, 0, 0, 163, 0, 177, 0, 0, 0, 0, 0, 0, 0, 0, 161, 161, 164, 164, 164, 164, 164, 164, 164, 164, 164, 164, 161, 0, 0, 0, 0, 0, 0, 0, 0, 0, 0, 0, 0, 0, 0, 0, 0, 163, 0, 0, 0, 0, 0, 0, 0, 0, 0, 0, 161, 161, 0, 0, 0, 0, 0, 0, 0, 0, 0, 0, 162, 0, 0, 0, 0, 0, 0, 0, 0, 0, 0, 0, 0, 0, 0, 0, 0, 161, 164, 164, 164, 164, 164, 164, 164, 164, 164, 164, 161, 161, 0, 0, 0, 0, 0, 0, 0, 0, 177, 0, 162, 0, 0, 0, 0, 0, 0, 0, 0, 0, 0, 0, 0, 0, 0, 0, 0, 161, 0, 0, 0, 0, 0, 0, 0, 0, 0, 0, 161, 161, 0, 0, 0, 0, 0, 0, 0, 0, 0, 0, 162, 0, 0, 0, 0, 0, 0, 0, 0, 0, 0, 0, 0, 0, 0, 0, 0, 161, 0, 177, 0, 0, 0, 0, 0, 0, 0, 0, 161, 161, 0, 0, 0, 0, 0, 0, 0, 0, 0, 0, 162, 0, 0, 0, 0, 0, 0, 0, 0, 0, 0, 0, 0, 0, 0, 0, 0, 161, 0, 0, 0, 0, 0, 0, 0, 0, 0, 0, 161, 161, 0, 0, 0, 0, 0, 0, 0, 0, 0, 0, 162, 0, 0, 0, 0, 0, 0, 0, 0, 0, 0, 0, 0, 0, 0, 0, 0, 161, 0, 0, 0, 0, 0, 0, 0, 0, 0, 0, 161, 161, 0, 0, 0, 0, 0, 0, 0, 0, 0, 0, 162, 0, 0, 0, 0, 0, 0, 0, 0, 0, 0, 0, 0, 0, 0, 0, 0, 161, 0, 0, 0, 0, 0, 0, 0, 0, 0, 0, 161, 161, 0, 0, 0, 0, 0, 0, 0, 0, 0, 0, 162, 0, 0, 0, 0, 0, 0, 0, 0, 0, 0, 0, 0, 0, 0, 0, 0, 161, 0, 0, 0, 0, 0, 0, 0, 0, 0, 0, 161, 161, 0, 0, 0, 0, 0, 0, 0, 0, 0, 0, 162, 0, 0, 0, 0, 0, 0, 0, 0, 0, 0, 0, 0, 0, 0, 0, 0, 161, 0, 0, 0, 0, 0, 0, 0, 0, 0, 0, 161, 161, 0, 0, 0, 0, 0, 0, 0, 0, 0, 0, 162, 0, 0, 0, 0, 0, 0, 0, 0, 0, 0, 0, 0, 0, 0, 0, 0, 161, 0, 0, 0, 0, 0, 0, 0, 0, 0, 0, 161, 161, 0, 176, 0, 0, 0, 0, 0, 0, 178, 0, 162, 0, 177, 0, 0, 0, 0, 0, 0, 0, 0, 0, 0, 0, 0, 176, 0, 161, 0, 178, 0, 0, 0, 0, 0, 0, 176, 0, 161, 161, 0, 0, 0, 0, 0, 0, 0, 0, 0, 0, 162, 0, 0, 0, 0, 0, 0, 0, 0, 0, 0, 0, 0, 0, 0, 0, 0, 161, 0, 0, 0, 0, 0, 0, 0, 0, 0, 0, 161, 161, 161, 161, 161, 161, 161, 161, 161, 161, 161, 161, 161, 161, 161, 161, 161, 161, 161, 161, 161, 161, 161, 161, 161, 161, 161, 161, 161, 161, 161, 161, 161, 161, 161, 161, 161, 161, 161, 161, 161, 0, 0, 0, 0, 0, 0, 0, 0, 0, 0, 0, 0, 0, 0, 0, 0, 0, 0, 0, 0, 0, 0, 0, 0, 0, 0, 0, 0, 0, 0, 0, 0, 0, 0, 0, 0, 0, 0, 0, 0],
         "height":25,
         "name":"tile_switcher",
         "opacity":1,
         "type":"tilelayer",
         "visible":false,
         "width":40,
         "x":0,
         "y":0
        }, 
        {
         "draworder":"topdown",
         "height":0,
         "name":"scene_switcher",
         "objects":[],
         "opacity":1,
         "properties":
            {
             "#tile":"tile_switcher",
             "set":"{\"_\":[\"stencil\",\"stageModel\"]}",
             "stageComment":"\"Switch the switch!\"",
             "stageName":"\"Switcher\"",
             "states":"{\n        \"name\":\"game\",\n        \"like\":[{\"_\":[\"stencil\",\"modelFoodKeeper\"]},{\"_\":[\"stencil\",\"modelSwitcher\"]}]\n      }"
            },
         "type":"objectgroup",
         "visible":false,
         "width":0,
         "x":0,
         "y":0
        }, 
        {
         "data":[0, 0, 0, 0, 0, 0, 0, 0, 0, 0, 0, 0, 0, 0, 0, 0, 0, 0, 0, 0, 0, 0, 0, 0, 0, 0, 0, 0, 0, 0, 0, 0, 0, 0, 0, 0, 0, 0, 0, 0, 169, 170, 170, 170, 170, 170, 170, 170, 170, 170, 170, 170, 170, 170, 170, 170, 170, 170, 170, 170, 170, 170, 170, 170, 170, 170, 170, 170, 170, 170, 170, 170, 170, 170, 170, 170, 170, 170, 170, 171, 168, 0, 0, 0, 0, 0, 0, 0, 0, 0, 0, 0, 0, 0, 0, 0, 0, 0, 0, 0, 0, 0, 0, 0, 0, 0, 0, 0, 0, 0, 0, 0, 0, 0, 0, 0, 0, 0, 0, 168, 168, 0, 0, 0, 0, 0, 0, 0, 0, 0, 0, 0, 0, 0, 0, 0, 0, 0, 0, 0, 0, 0, 0, 0, 0, 0, 0, 0, 0, 0, 0, 0, 0, 0, 0, 0, 0, 0, 0, 168, 168, 0, 0, 0, 0, 0, 0, 0, 0, 0, 0, 0, 0, 0, 0, 0, 0, 0, 0, 0, 0, 0, 0, 0, 0, 0, 0, 0, 0, 0, 0, 0, 0, 0, 0, 0, 0, 0, 0, 168, 168, 0, 0, 0, 0, 0, 0, 0, 0, 0, 0, 0, 0, 0, 0, 0, 0, 0, 0, 0, 0, 0, 0, 0, 0, 0, 0, 0, 0, 0, 0, 0, 0, 0, 0, 0, 0, 0, 0, 168, 168, 0, 0, 0, 0, 0, 0, 0, 0, 0, 0, 0, 0, 0, 0, 0, 0, 0, 0, 0, 0, 0, 0, 0, 0, 0, 0, 0, 0, 0, 0, 0, 0, 0, 0, 0, 0, 0, 0, 168, 168, 0, 0, 0, 0, 0, 0, 0, 0, 0, 0, 0, 168, 0, 0, 0, 0, 0, 0, 0, 0, 0, 0, 0, 0, 0, 0, 168, 0, 0, 0, 0, 0, 0, 0, 0, 0, 0, 0, 168, 168, 0, 0, 0, 0, 0, 0, 0, 0, 0, 0, 0, 168, 0, 0, 0, 0, 0, 0, 0, 0, 0, 0, 0, 0, 0, 0, 168, 0, 0, 0, 0, 0, 0, 0, 0, 0, 0, 0, 168, 168, 0, 0, 0, 0, 0, 0, 0, 0, 0, 0, 0, 168, 0, 0, 0, 0, 0, 0, 0, 0, 0, 0, 0, 0, 0, 0, 168, 0, 0, 0, 0, 0, 0, 0, 0, 0, 0, 0, 168, 168, 0, 0, 0, 0, 0, 0, 0, 0, 0, 0, 0, 168, 0, 0, 0, 0, 0, 0, 0, 0, 0, 0, 0, 0, 0, 0, 168, 0, 0, 0, 0, 0, 0, 0, 0, 0, 0, 0, 168, 168, 0, 0, 0, 0, 0, 0, 0, 0, 0, 0, 0, 175, 174, 174, 174, 174, 174, 174, 174, 174, 174, 174, 174, 174, 174, 174, 173, 0, 0, 0, 0, 0, 0, 0, 0, 0, 0, 0, 168, 168, 0, 0, 0, 0, 0, 0, 0, 0, 0, 0, 0, 0, 0, 0, 0, 0, 0, 0, 0, 0, 0, 0, 0, 0, 0, 0, 0, 0, 0, 0, 0, 0, 0, 0, 0, 0, 0, 0, 168, 168, 0, 0, 0, 0, 0, 0, 0, 0, 0, 0, 0, 0, 0, 0, 0, 0, 0, 0, 0, 0, 0, 0, 0, 0, 0, 0, 0, 0, 0, 0, 0, 0, 0, 0, 0, 0, 0, 0, 168, 168, 0, 0, 0, 0, 0, 0, 0, 0, 0, 0, 0, 0, 0, 0, 0, 0, 0, 0, 0, 0, 0, 0, 0, 0, 0, 0, 0, 0, 0, 0, 0, 0, 0, 0, 0, 0, 0, 0, 168, 168, 0, 0, 0, 0, 0, 0, 0, 0, 0, 0, 0, 0, 0, 0, 0, 0, 0, 0, 0, 0, 0, 0, 0, 0, 0, 0, 0, 0, 0, 0, 0, 0, 0, 0, 0, 0, 0, 0, 168, 168, 0, 0, 0, 0, 0, 0, 0, 0, 0, 0, 0, 0, 0, 0, 0, 0, 0, 0, 0, 0, 0, 0, 0, 0, 0, 0, 0, 0, 0, 0, 0, 0, 0, 0, 0, 0, 0, 0, 168, 168, 0, 0, 0, 0, 0, 0, 0, 0, 0, 0, 0, 0, 0, 0, 0, 0, 0, 0, 0, 0, 0, 0, 0, 0, 0, 0, 0, 0, 0, 0, 0, 0, 0, 0, 0, 0, 0, 0, 168, 168, 0, 0, 0, 0, 0, 0, 0, 0, 0, 0, 0, 0, 0, 0, 0, 0, 0, 0, 0, 0, 0, 0, 0, 0, 0, 0, 0, 0, 0, 0, 0, 0, 0, 0, 0, 0, 0, 0, 168, 168, 0, 0, 0, 0, 0, 0, 0, 0, 0, 0, 0, 0, 0, 0, 0, 0, 0, 0, 0, 0, 0, 0, 0, 0, 0, 0, 0, 0, 0, 0, 0, 0, 0, 0, 0, 0, 0, 0, 168, 168, 0, 0, 0, 0, 0, 0, 0, 0, 0, 0, 0, 0, 0, 0, 0, 0, 0, 0, 0, 0, 0, 0, 0, 0, 0, 0, 0, 0, 0, 0, 0, 0, 0, 0, 0, 0, 0, 0, 168, 168, 0, 0, 0, 0, 0, 0, 0, 0, 0, 0, 0, 0, 0, 0, 0, 0, 0, 0, 0, 0, 0, 0, 0, 0, 0, 0, 0, 0, 0, 0, 0, 0, 0, 0, 0, 0, 0, 0, 168, 168, 0, 0, 0, 0, 0, 0, 0, 0, 0, 0, 0, 0, 0, 0, 0, 0, 0, 0, 0, 0, 0, 0, 0, 0, 0, 0, 0, 0, 0, 0, 0, 0, 0, 0, 0, 0, 0, 0, 168, 175, 174, 174, 174, 174, 174, 174, 174, 174, 174, 174, 174, 174, 174, 174, 174, 174, 174, 174, 174, 174, 174, 174, 174, 174, 174, 174, 174, 174, 174, 174, 174, 174, 174, 174, 174, 174, 174, 174, 173, 0, 0, 0, 0, 0, 0, 0, 0, 0, 0, 0, 0, 0, 0, 0, 0, 0, 0, 0, 0, 0, 0, 0, 0, 0, 0, 0, 0, 0, 0, 0, 0, 0, 0, 0, 0, 0, 0, 0, 0],
         "height":25,
         "name":"tile_rolly",
         "opacity":1,
         "type":"tilelayer",
         "visible":false,
         "width":40,
         "x":0,
         "y":0
        }, 
        {
         "draworder":"topdown",
         "height":0,
         "name":"scene_rolly",
         "objects":[],
         "opacity":1,
         "properties":
            {
             "#tile":"tile_rolly",
             "backgroundTileX":"8",
             "set":"{\"_\":[\"stencil\",\"stageModel\"]}",
             "shadowX":"0",
             "shadowY":"0",
             "snakeTileY":"16",
             "stageComment":"\"Avoid the bad guys!\"",
             "stageName":"\"Rolly\"",
             "startY":"21",
             "states":"{\n        \"name\":\"game\",\n        \"like\":[{\"_\":[\"stencil\",\"modelFoodKeeper\"]},{\"_\":[\"stencil\",\"modelRolly\"]}]\n      }"
            },
         "type":"objectgroup",
         "visible":false,
         "width":0,
         "x":0,
         "y":0
        }, 
        {
         "data":[0, 0, 0, 0, 0, 0, 0, 0, 0, 0, 0, 0, 0, 0, 0, 0, 0, 0, 0, 0, 0, 0, 0, 0, 0, 0, 0, 0, 0, 0, 0, 0, 0, 0, 0, 0, 0, 0, 0, 0, 167, 167, 167, 167, 167, 167, 167, 167, 167, 167, 167, 167, 167, 167, 0, 0, 0, 0, 0, 0, 0, 0, 0, 0, 0, 0, 167, 167, 167, 167, 167, 167, 167, 167, 167, 167, 167, 167, 167, 167, 167, 0, 0, 0, 0, 0, 0, 0, 0, 0, 0, 0, 0, 0, 0, 0, 0, 0, 0, 0, 0, 0, 0, 0, 0, 0, 0, 0, 0, 0, 0, 0, 0, 0, 0, 0, 0, 0, 0, 167, 167, 0, 0, 0, 0, 0, 0, 0, 0, 0, 0, 0, 0, 0, 0, 0, 0, 0, 0, 0, 0, 0, 0, 0, 0, 0, 0, 0, 0, 0, 0, 0, 0, 0, 0, 0, 0, 0, 0, 167, 167, 0, 0, 0, 0, 0, 0, 0, 0, 0, 0, 0, 0, 0, 0, 0, 0, 0, 0, 0, 0, 0, 0, 0, 0, 0, 0, 0, 0, 0, 0, 0, 0, 0, 0, 0, 0, 0, 0, 167, 167, 0, 0, 0, 0, 0, 0, 0, 0, 0, 0, 0, 0, 0, 0, 0, 0, 0, 0, 0, 0, 0, 0, 0, 0, 0, 0, 0, 0, 0, 0, 0, 0, 0, 0, 0, 0, 0, 0, 167, 167, 0, 0, 0, 0, 0, 0, 0, 0, 0, 0, 0, 0, 0, 0, 0, 0, 0, 0, 0, 0, 0, 0, 0, 0, 0, 0, 0, 0, 0, 0, 0, 0, 0, 0, 0, 0, 0, 0, 167, 167, 0, 0, 0, 0, 0, 0, 0, 0, 0, 0, 0, 0, 0, 0, 0, 0, 0, 0, 0, 0, 0, 0, 0, 0, 0, 0, 0, 0, 0, 0, 0, 0, 0, 0, 0, 0, 0, 0, 167, 167, 0, 0, 0, 0, 0, 0, 0, 0, 0, 0, 0, 0, 167, 167, 167, 167, 0, 0, 0, 0, 0, 0, 167, 167, 167, 167, 0, 0, 0, 0, 0, 0, 0, 0, 0, 0, 0, 0, 167, 167, 0, 0, 0, 0, 0, 0, 0, 0, 0, 0, 0, 0, 0, 0, 0, 0, 0, 0, 0, 0, 0, 0, 0, 0, 0, 0, 0, 0, 0, 0, 0, 0, 0, 0, 0, 0, 0, 0, 167, 167, 0, 0, 0, 0, 0, 0, 0, 0, 0, 0, 0, 0, 0, 0, 0, 0, 0, 0, 0, 0, 0, 0, 0, 0, 0, 0, 0, 0, 0, 0, 0, 0, 0, 0, 0, 0, 0, 0, 167, 167, 0, 0, 0, 0, 0, 0, 0, 0, 0, 0, 0, 0, 0, 0, 0, 0, 0, 0, 0, 0, 0, 0, 0, 0, 0, 0, 0, 0, 0, 0, 0, 0, 0, 0, 0, 0, 0, 0, 167, 167, 0, 0, 0, 0, 0, 0, 0, 0, 0, 0, 0, 0, 0, 0, 0, 0, 0, 0, 0, 0, 0, 0, 0, 0, 0, 0, 0, 0, 0, 0, 0, 0, 0, 0, 0, 0, 0, 0, 167, 167, 0, 0, 0, 0, 0, 0, 0, 0, 0, 0, 0, 0, 0, 0, 0, 0, 0, 0, 0, 0, 0, 0, 0, 0, 0, 0, 0, 0, 0, 0, 0, 0, 0, 0, 0, 0, 0, 0, 167, 167, 0, 0, 0, 0, 0, 0, 0, 0, 0, 0, 0, 0, 0, 0, 0, 0, 0, 0, 0, 0, 0, 0, 0, 0, 0, 0, 0, 0, 0, 0, 0, 0, 0, 0, 0, 0, 0, 0, 167, 167, 0, 0, 0, 0, 0, 0, 0, 0, 0, 0, 0, 0, 0, 0, 0, 0, 0, 0, 0, 0, 0, 0, 0, 0, 0, 0, 0, 0, 0, 0, 0, 0, 0, 0, 0, 0, 0, 0, 167, 167, 0, 0, 0, 0, 0, 0, 0, 0, 0, 0, 0, 0, 167, 167, 167, 167, 0, 0, 0, 0, 0, 0, 167, 167, 167, 167, 0, 0, 0, 0, 0, 0, 0, 0, 0, 0, 0, 0, 167, 167, 0, 0, 0, 0, 0, 0, 0, 0, 0, 0, 0, 0, 0, 0, 0, 0, 0, 0, 0, 0, 0, 0, 0, 0, 0, 0, 0, 0, 0, 0, 0, 0, 0, 0, 0, 0, 0, 0, 167, 167, 0, 0, 0, 0, 0, 0, 0, 0, 0, 0, 0, 0, 0, 0, 0, 0, 0, 0, 0, 0, 0, 0, 0, 0, 0, 0, 0, 0, 0, 0, 0, 0, 0, 0, 0, 0, 0, 0, 167, 167, 0, 0, 0, 0, 0, 0, 0, 0, 0, 0, 0, 0, 0, 0, 0, 0, 0, 0, 0, 0, 0, 0, 0, 0, 0, 0, 0, 0, 0, 0, 0, 0, 0, 0, 0, 0, 0, 0, 167, 167, 0, 0, 0, 0, 0, 0, 0, 0, 0, 0, 0, 0, 0, 0, 0, 0, 0, 0, 0, 0, 0, 0, 0, 0, 0, 0, 0, 0, 0, 0, 0, 0, 0, 0, 0, 0, 0, 0, 167, 167, 0, 0, 0, 0, 0, 0, 0, 0, 0, 0, 0, 0, 0, 0, 0, 0, 0, 0, 0, 0, 0, 0, 0, 0, 0, 0, 0, 0, 0, 0, 0, 0, 0, 0, 0, 0, 0, 0, 167, 167, 0, 0, 0, 0, 0, 0, 0, 0, 0, 0, 0, 0, 0, 0, 0, 0, 0, 0, 0, 0, 0, 0, 0, 0, 0, 0, 0, 0, 0, 0, 0, 0, 0, 0, 0, 0, 0, 0, 167, 167, 167, 167, 167, 167, 167, 167, 167, 167, 167, 167, 167, 167, 167, 0, 0, 0, 0, 0, 0, 0, 0, 0, 0, 0, 0, 167, 167, 167, 167, 167, 167, 167, 167, 167, 167, 167, 167, 167, 167, 0, 0, 0, 0, 0, 0, 0, 0, 0, 0, 0, 0, 0, 0, 0, 0, 0, 0, 0, 0, 0, 0, 0, 0, 0, 0, 0, 0, 0, 0, 0, 0, 0, 0, 0, 0, 0, 0, 0, 0],
         "height":25,
         "name":"tile_spooky",
         "opacity":1,
         "type":"tilelayer",
         "visible":false,
         "width":40,
         "x":0,
         "y":0
        }, 
        {
         "draworder":"topdown",
         "height":0,
         "name":"scene_spooky",
         "objects":[],
         "opacity":1,
         "properties":
            {
             "#tile":"tile_spooky",
             "backgroundTileY":"8",
             "set":"{\"_\":[\"stencil\",\"stageModel\"]}",
             "snakeTileY":"48",
             "stageComment":"\"Alone in the dark!\"",
             "stageName":"\"Spooky\"",
             "states":"{\n        \"name\":\"game\",\n        \"like\":[{\"_\":[\"stencil\",\"modelFoodKeeper\"]},{\"_\":[\"stencil\",\"modelSpooky\"]}]\n      }",
             "targetLength":"30"
            },
         "type":"objectgroup",
         "visible":false,
         "width":0,
         "x":0,
         "y":0
        }, 
        {
         "data":[0, 0, 0, 0, 0, 0, 0, 0, 0, 0, 0, 0, 0, 0, 0, 0, 0, 0, 0, 0, 0, 0, 0, 0, 0, 0, 0, 0, 0, 0, 0, 0, 0, 0, 0, 0, 0, 0, 0, 0, 166, 166, 166, 166, 166, 166, 166, 166, 166, 166, 166, 166, 166, 166, 166, 166, 166, 166, 166, 166, 166, 166, 166, 166, 166, 166, 166, 166, 166, 166, 166, 166, 166, 166, 166, 166, 166, 166, 166, 166, 166, 0, 0, 0, 0, 0, 0, 0, 0, 0, 0, 0, 0, 0, 0, 0, 0, 0, 0, 0, 0, 0, 0, 0, 0, 0, 0, 0, 0, 0, 0, 0, 0, 0, 0, 0, 0, 0, 0, 166, 166, 0, 0, 0, 0, 0, 0, 0, 0, 0, 0, 0, 0, 0, 0, 0, 0, 0, 0, 0, 0, 0, 0, 0, 0, 0, 0, 0, 0, 0, 0, 0, 0, 0, 0, 0, 0, 0, 0, 166, 166, 0, 0, 166, 166, 0, 0, 0, 0, 166, 166, 0, 0, 0, 0, 166, 166, 0, 0, 0, 0, 0, 0, 0, 166, 166, 0, 0, 0, 0, 166, 166, 0, 0, 0, 0, 166, 166, 0, 166, 166, 0, 0, 0, 0, 0, 0, 0, 0, 0, 0, 0, 0, 0, 0, 0, 0, 0, 0, 0, 0, 0, 0, 0, 0, 0, 0, 0, 0, 0, 0, 0, 0, 0, 0, 0, 0, 0, 0, 166, 166, 0, 0, 166, 166, 0, 0, 0, 0, 166, 166, 0, 0, 0, 0, 166, 166, 0, 0, 0, 0, 0, 0, 0, 166, 166, 0, 0, 0, 0, 166, 166, 0, 0, 0, 0, 166, 166, 0, 166, 166, 0, 0, 0, 0, 0, 0, 0, 0, 0, 0, 0, 0, 0, 0, 0, 0, 0, 0, 0, 0, 0, 0, 0, 0, 0, 0, 0, 0, 0, 0, 0, 0, 0, 0, 0, 0, 0, 0, 166, 166, 0, 0, 0, 0, 0, 0, 0, 0, 0, 0, 0, 0, 0, 0, 0, 0, 0, 0, 0, 0, 0, 0, 0, 0, 0, 0, 0, 0, 0, 0, 0, 0, 0, 0, 0, 0, 0, 0, 166, 166, 0, 0, 0, 0, 0, 0, 0, 0, 0, 0, 0, 0, 0, 0, 0, 0, 0, 0, 0, 0, 0, 0, 0, 0, 0, 0, 0, 0, 0, 0, 0, 0, 0, 0, 0, 0, 0, 0, 166, 166, 0, 0, 0, 0, 0, 0, 0, 0, 0, 0, 0, 0, 0, 0, 0, 0, 0, 0, 0, 0, 0, 0, 0, 0, 0, 0, 0, 0, 0, 0, 0, 0, 0, 0, 0, 0, 0, 0, 166, 166, 0, 0, 0, 0, 0, 0, 0, 0, 0, 0, 0, 0, 0, 0, 0, 0, 0, 0, 0, 0, 0, 0, 0, 0, 0, 0, 0, 0, 0, 0, 0, 0, 0, 0, 0, 0, 0, 0, 166, 166, 0, 0, 0, 0, 0, 0, 0, 0, 0, 0, 0, 0, 0, 0, 0, 0, 0, 0, 0, 0, 0, 0, 0, 0, 0, 0, 0, 0, 0, 0, 0, 0, 0, 0, 0, 0, 0, 0, 166, 166, 0, 0, 0, 0, 0, 0, 0, 0, 0, 0, 0, 0, 0, 0, 0, 0, 0, 0, 0, 0, 0, 0, 0, 0, 0, 0, 0, 0, 0, 0, 0, 0, 0, 0, 0, 0, 0, 0, 166, 166, 0, 0, 0, 0, 0, 0, 0, 0, 0, 0, 0, 0, 0, 0, 0, 0, 0, 0, 0, 0, 0, 0, 0, 0, 0, 0, 0, 0, 0, 0, 0, 0, 0, 0, 0, 0, 0, 0, 166, 166, 0, 0, 0, 0, 0, 0, 0, 0, 0, 0, 0, 0, 0, 0, 0, 0, 0, 0, 0, 0, 0, 0, 0, 0, 0, 0, 0, 0, 0, 0, 0, 0, 0, 0, 0, 0, 0, 0, 166, 166, 0, 0, 0, 0, 0, 0, 0, 0, 0, 0, 0, 0, 0, 0, 0, 0, 0, 0, 0, 0, 0, 0, 0, 0, 0, 0, 0, 0, 0, 0, 0, 0, 0, 0, 0, 0, 0, 0, 166, 166, 0, 0, 0, 0, 0, 0, 0, 0, 0, 0, 0, 0, 0, 0, 0, 0, 0, 0, 0, 0, 0, 0, 0, 0, 0, 0, 0, 0, 0, 0, 0, 0, 0, 0, 0, 0, 0, 0, 166, 166, 0, 0, 0, 0, 0, 0, 0, 0, 0, 0, 0, 0, 0, 0, 0, 0, 0, 0, 0, 0, 0, 0, 0, 0, 0, 0, 0, 0, 0, 0, 0, 0, 0, 0, 0, 0, 0, 0, 166, 166, 0, 0, 0, 0, 0, 0, 0, 0, 0, 0, 0, 0, 0, 0, 0, 0, 0, 0, 0, 0, 0, 0, 0, 0, 0, 0, 0, 0, 0, 0, 0, 0, 0, 0, 0, 0, 0, 0, 166, 166, 0, 0, 0, 0, 0, 0, 0, 0, 0, 0, 0, 0, 0, 0, 0, 0, 0, 0, 0, 0, 0, 0, 0, 0, 0, 0, 0, 0, 0, 0, 0, 0, 0, 0, 0, 0, 0, 0, 166, 166, 0, 0, 0, 0, 0, 0, 0, 0, 0, 0, 0, 0, 0, 0, 0, 0, 0, 0, 0, 0, 0, 0, 0, 0, 0, 0, 0, 0, 0, 0, 0, 0, 0, 0, 0, 0, 0, 0, 166, 166, 0, 0, 0, 0, 0, 0, 0, 0, 0, 0, 0, 0, 0, 0, 0, 0, 0, 0, 0, 0, 0, 0, 0, 0, 0, 0, 0, 0, 0, 0, 0, 0, 0, 0, 0, 0, 0, 0, 166, 166, 166, 166, 0, 0, 0, 0, 0, 0, 0, 0, 0, 0, 0, 0, 0, 0, 0, 0, 0, 0, 0, 0, 0, 0, 0, 0, 0, 0, 0, 0, 0, 0, 0, 0, 0, 0, 166, 166, 166, 0, 0, 0, 0, 0, 0, 0, 0, 0, 0, 0, 0, 0, 0, 0, 0, 0, 0, 0, 0, 0, 0, 0, 0, 0, 0, 0, 0, 0, 0, 0, 0, 0, 0, 0, 0, 0, 0, 0, 0],
         "height":25,
         "name":"tile_baller",
         "opacity":1,
         "type":"tilelayer",
         "visible":false,
         "width":40,
         "x":0,
         "y":0
        }, 
        {
         "draworder":"topdown",
         "height":0,
         "name":"scene_baller",
         "objects":[],
         "opacity":1,
         "properties":
            {
             "#tile":"tile_baller",
             "set":"{\"_\":[\"stencil\",\"stageModel\"]}",
             "snakeSpeed":"2",
             "snakeTileY":"40",
             "stageComment":"\"Don't let the ball fall!\"",
             "stageName":"\"Baller\"",
             "startSnakeFood":"5",
             "startY":"21",
             "states":"{\n        \"name\":\"game\",\n        \"like\":[{\"_\":[\"stencil\",\"modelFoodKeeper\"]},{\"_\":[\"stencil\",\"modelBaller\"]}]\n      }"
            },
         "type":"objectgroup",
         "visible":false,
         "width":0,
         "x":0,
         "y":0
        }, 
        {
         "data":[0, 0, 0, 0, 0, 0, 0, 0, 0, 0, 0, 0, 0, 0, 0, 0, 0, 0, 0, 0, 0, 0, 0, 0, 0, 0, 0, 0, 0, 0, 0, 0, 0, 0, 0, 0, 0, 0, 0, 0, 165, 165, 165, 165, 165, 165, 165, 165, 165, 165, 165, 165, 165, 165, 165, 165, 165, 165, 165, 165, 165, 165, 165, 165, 165, 165, 165, 165, 165, 165, 165, 165, 165, 165, 165, 165, 165, 165, 165, 165, 165, 0, 0, 0, 0, 0, 0, 0, 0, 0, 0, 0, 0, 0, 0, 0, 0, 0, 0, 0, 0, 0, 0, 0, 0, 0, 0, 0, 0, 0, 0, 0, 0, 0, 0, 0, 0, 0, 0, 165, 165, 0, 0, 0, 0, 0, 0, 0, 0, 0, 0, 0, 0, 0, 0, 0, 0, 0, 0, 0, 0, 0, 0, 0, 0, 0, 0, 0, 0, 0, 0, 0, 0, 0, 0, 0, 0, 0, 0, 165, 165, 0, 0, 0, 0, 0, 0, 0, 0, 0, 0, 0, 0, 0, 0, 0, 0, 0, 0, 0, 0, 0, 0, 0, 0, 0, 0, 0, 0, 0, 0, 0, 0, 0, 0, 0, 0, 0, 0, 165, 165, 0, 0, 0, 0, 0, 0, 0, 0, 0, 0, 0, 0, 0, 0, 0, 0, 0, 0, 0, 0, 0, 0, 0, 0, 0, 0, 0, 0, 0, 0, 0, 0, 0, 0, 0, 0, 0, 0, 165, 165, 0, 0, 0, 0, 0, 0, 0, 0, 0, 0, 0, 0, 0, 0, 0, 0, 0, 0, 0, 0, 0, 0, 0, 0, 0, 0, 0, 0, 0, 0, 0, 0, 0, 0, 0, 0, 0, 0, 165, 165, 0, 0, 0, 0, 0, 0, 165, 0, 0, 0, 0, 0, 0, 0, 0, 0, 0, 0, 0, 0, 0, 0, 0, 0, 0, 0, 0, 0, 0, 0, 0, 165, 0, 0, 0, 0, 0, 0, 165, 165, 0, 0, 0, 0, 0, 0, 165, 0, 0, 0, 0, 0, 0, 0, 0, 0, 0, 0, 0, 0, 0, 0, 0, 0, 0, 0, 0, 0, 0, 0, 0, 165, 0, 0, 0, 0, 0, 0, 165, 165, 0, 0, 0, 0, 0, 0, 165, 0, 0, 0, 0, 0, 0, 0, 0, 0, 0, 0, 0, 0, 0, 0, 0, 0, 0, 0, 0, 0, 0, 0, 0, 165, 0, 0, 0, 0, 0, 0, 165, 165, 0, 0, 0, 0, 0, 0, 165, 0, 0, 0, 0, 0, 0, 0, 0, 0, 0, 0, 0, 0, 0, 0, 0, 0, 0, 0, 0, 0, 0, 0, 0, 165, 0, 0, 0, 0, 0, 0, 165, 165, 0, 0, 0, 0, 0, 0, 165, 0, 0, 0, 0, 0, 0, 0, 0, 0, 0, 0, 0, 0, 0, 0, 0, 0, 0, 0, 0, 0, 0, 0, 0, 165, 0, 0, 0, 0, 0, 0, 165, 165, 0, 0, 0, 0, 0, 0, 165, 0, 0, 0, 0, 0, 0, 0, 0, 0, 0, 0, 0, 0, 0, 0, 0, 0, 0, 0, 0, 0, 0, 0, 0, 165, 0, 0, 0, 0, 0, 0, 165, 165, 0, 0, 0, 0, 0, 0, 165, 0, 0, 0, 0, 0, 0, 0, 0, 0, 0, 0, 0, 0, 0, 0, 0, 0, 0, 0, 0, 0, 0, 0, 0, 165, 0, 0, 0, 0, 0, 0, 165, 165, 0, 0, 0, 0, 0, 0, 165, 0, 0, 0, 0, 0, 0, 0, 0, 0, 0, 0, 0, 0, 0, 0, 0, 0, 0, 0, 0, 0, 0, 0, 0, 165, 0, 0, 0, 0, 0, 0, 165, 165, 0, 0, 0, 0, 0, 0, 165, 0, 0, 0, 0, 0, 0, 0, 0, 0, 0, 0, 0, 0, 0, 0, 0, 0, 0, 0, 0, 0, 0, 0, 0, 165, 0, 0, 0, 0, 0, 0, 165, 165, 0, 0, 0, 0, 0, 0, 165, 0, 0, 0, 0, 0, 0, 0, 0, 0, 0, 0, 0, 0, 0, 0, 0, 0, 0, 0, 0, 0, 0, 0, 0, 165, 0, 0, 0, 0, 0, 0, 165, 165, 0, 0, 0, 0, 0, 0, 165, 165, 165, 165, 165, 165, 165, 165, 165, 165, 165, 165, 165, 165, 165, 165, 165, 165, 165, 165, 165, 165, 165, 165, 165, 165, 0, 0, 0, 0, 0, 0, 165, 165, 0, 0, 0, 0, 0, 0, 0, 0, 0, 0, 0, 0, 0, 0, 0, 0, 0, 0, 0, 0, 0, 0, 0, 0, 0, 0, 0, 0, 0, 0, 0, 0, 0, 0, 0, 0, 0, 0, 165, 165, 0, 0, 0, 0, 0, 0, 0, 0, 0, 0, 0, 0, 0, 0, 0, 0, 0, 0, 0, 0, 0, 0, 0, 0, 0, 0, 0, 0, 0, 0, 0, 0, 0, 0, 0, 0, 0, 0, 165, 165, 0, 0, 0, 0, 0, 0, 0, 0, 0, 0, 0, 0, 0, 0, 0, 0, 0, 0, 0, 0, 0, 0, 0, 0, 0, 0, 0, 0, 0, 0, 0, 0, 0, 0, 0, 0, 0, 0, 165, 165, 0, 0, 0, 0, 0, 0, 0, 0, 0, 0, 0, 0, 0, 0, 0, 0, 0, 0, 0, 0, 0, 0, 0, 0, 0, 0, 0, 0, 0, 0, 0, 0, 0, 0, 0, 0, 0, 0, 165, 165, 0, 0, 0, 0, 0, 0, 0, 0, 0, 0, 0, 0, 0, 0, 0, 0, 0, 0, 0, 0, 0, 0, 0, 0, 0, 0, 0, 0, 0, 0, 0, 0, 0, 0, 0, 0, 0, 0, 165, 165, 165, 165, 165, 165, 165, 165, 165, 165, 165, 165, 165, 165, 165, 165, 165, 165, 165, 165, 165, 165, 165, 165, 165, 165, 165, 165, 165, 165, 165, 165, 165, 165, 165, 165, 165, 165, 165, 165, 165, 0, 0, 0, 0, 0, 0, 0, 0, 0, 0, 0, 0, 0, 0, 0, 0, 0, 0, 0, 0, 0, 0, 0, 0, 0, 0, 0, 0, 0, 0, 0, 0, 0, 0, 0, 0, 0, 0, 0, 0],
         "height":25,
         "name":"tile_multi",
         "opacity":1,
         "type":"tilelayer",
         "visible":false,
         "width":40,
         "x":0,
         "y":0
        }, 
        {
         "draworder":"topdown",
         "height":0,
         "name":"scene_multi",
         "objects":[],
         "opacity":1,
         "properties":
            {
             "#tile":"tile_multi",
             "foodToKeep":"10",
             "set":"{\"_\":[\"stencil\",\"stageModel\"]}",
             "stageComment":"\"Eat! Eat! Eat!\"",
             "stageName":"\"Multi\"",
             "startY":"21",
             "states":"{\n        \"name\":\"game\",\n        \"like\":{\"_\":[\"stencil\",\"modelFoodKeeper\"]}\n      }"
            },
         "type":"objectgroup",
         "visible":false,
         "width":0,
         "x":0,
         "y":0
        }, 
        {
         "data":[0, 0, 0, 0, 0, 0, 0, 0, 0, 0, 0, 0, 0, 0, 0, 0, 0, 0, 0, 0, 0, 0, 0, 0, 0, 0, 0, 0, 0, 0, 0, 0, 0, 0, 0, 0, 0, 0, 0, 0, 164, 164, 164, 164, 164, 164, 164, 164, 164, 164, 164, 164, 164, 164, 164, 164, 164, 164, 164, 164, 164, 164, 164, 164, 164, 164, 164, 164, 164, 164, 164, 164, 164, 164, 164, 164, 164, 164, 164, 164, 164, 0, 0, 0, 0, 0, 0, 0, 0, 0, 0, 0, 0, 0, 0, 0, 0, 0, 0, 0, 0, 0, 0, 0, 0, 0, 0, 0, 0, 0, 0, 0, 0, 0, 0, 0, 0, 0, 0, 164, 164, 0, 0, 0, 0, 0, 0, 0, 0, 0, 0, 0, 0, 0, 0, 0, 0, 0, 0, 0, 0, 0, 0, 0, 0, 0, 0, 0, 0, 0, 0, 0, 0, 0, 0, 0, 0, 0, 0, 164, 164, 0, 0, 0, 0, 0, 0, 0, 0, 0, 0, 0, 0, 0, 0, 0, 0, 0, 0, 0, 0, 0, 0, 0, 0, 0, 0, 0, 0, 0, 0, 0, 0, 0, 0, 0, 0, 0, 0, 164, 164, 0, 0, 0, 0, 0, 0, 0, 0, 0, 0, 0, 0, 0, 0, 0, 0, 0, 0, 0, 0, 0, 0, 0, 0, 0, 0, 0, 0, 0, 0, 0, 0, 0, 0, 0, 0, 0, 0, 164, 164, 0, 0, 0, 0, 0, 0, 0, 0, 0, 0, 0, 0, 0, 0, 0, 0, 0, 0, 0, 0, 0, 0, 0, 0, 0, 0, 0, 0, 0, 0, 0, 0, 0, 0, 0, 0, 0, 0, 164, 164, 0, 0, 0, 0, 0, 164, 164, 164, 164, 0, 0, 0, 0, 0, 0, 0, 0, 0, 164, 164, 0, 0, 0, 0, 0, 0, 0, 0, 0, 164, 164, 164, 164, 0, 0, 0, 0, 0, 164, 164, 0, 0, 0, 0, 0, 164, 0, 0, 0, 0, 0, 0, 0, 0, 0, 0, 0, 0, 164, 164, 0, 0, 0, 0, 0, 0, 0, 0, 0, 0, 0, 0, 164, 0, 0, 0, 0, 0, 164, 164, 0, 0, 0, 0, 0, 164, 0, 0, 0, 0, 0, 0, 0, 0, 0, 0, 0, 0, 164, 164, 0, 0, 0, 0, 0, 0, 0, 0, 0, 0, 0, 0, 164, 0, 0, 0, 0, 0, 164, 164, 0, 0, 0, 0, 0, 164, 0, 0, 0, 0, 0, 0, 0, 0, 0, 0, 0, 0, 164, 164, 0, 0, 0, 0, 0, 0, 0, 0, 0, 0, 0, 0, 164, 0, 0, 0, 0, 0, 164, 164, 0, 0, 0, 0, 0, 164, 0, 0, 0, 0, 0, 0, 0, 0, 0, 0, 0, 0, 164, 164, 0, 0, 0, 0, 0, 0, 0, 0, 0, 0, 0, 0, 164, 0, 0, 0, 0, 0, 164, 164, 0, 0, 0, 0, 0, 164, 0, 0, 0, 0, 0, 0, 0, 0, 0, 0, 0, 0, 164, 164, 0, 0, 0, 0, 0, 0, 0, 0, 0, 0, 0, 0, 164, 0, 0, 0, 0, 0, 164, 164, 0, 0, 0, 0, 0, 164, 0, 0, 0, 0, 0, 0, 0, 0, 0, 0, 0, 0, 164, 164, 0, 0, 0, 0, 0, 0, 0, 0, 0, 0, 0, 0, 164, 0, 0, 0, 0, 0, 164, 164, 0, 0, 0, 0, 0, 164, 0, 0, 0, 0, 0, 0, 0, 0, 0, 0, 0, 0, 164, 164, 0, 0, 0, 0, 0, 0, 0, 0, 0, 0, 0, 0, 164, 0, 0, 0, 0, 0, 164, 164, 0, 0, 0, 0, 0, 164, 0, 0, 0, 0, 0, 0, 0, 0, 0, 0, 0, 0, 164, 164, 0, 0, 0, 0, 0, 0, 0, 0, 0, 0, 0, 0, 164, 0, 0, 0, 0, 0, 164, 164, 0, 0, 0, 0, 0, 164, 0, 0, 0, 0, 0, 0, 0, 0, 0, 0, 0, 0, 164, 164, 0, 0, 0, 0, 0, 0, 0, 0, 0, 0, 0, 0, 164, 0, 0, 0, 0, 0, 164, 164, 0, 0, 0, 0, 0, 164, 164, 164, 164, 0, 0, 0, 0, 0, 0, 0, 0, 0, 164, 164, 0, 0, 0, 0, 0, 0, 0, 0, 0, 164, 164, 164, 164, 0, 0, 0, 0, 0, 164, 164, 0, 0, 0, 0, 0, 0, 0, 0, 0, 0, 0, 0, 0, 0, 0, 0, 0, 0, 0, 0, 0, 0, 0, 0, 0, 0, 0, 0, 0, 0, 0, 0, 0, 0, 0, 0, 0, 0, 164, 164, 0, 0, 0, 0, 0, 0, 0, 0, 0, 0, 0, 0, 0, 0, 0, 0, 0, 0, 0, 0, 0, 0, 0, 0, 0, 0, 0, 0, 0, 0, 0, 0, 0, 0, 0, 0, 0, 0, 164, 164, 0, 0, 0, 0, 0, 0, 0, 0, 0, 0, 0, 0, 0, 0, 0, 0, 0, 0, 0, 0, 0, 0, 0, 0, 0, 0, 0, 0, 0, 0, 0, 0, 0, 0, 0, 0, 0, 0, 164, 164, 0, 0, 0, 0, 0, 0, 0, 0, 0, 0, 0, 0, 0, 0, 0, 0, 0, 0, 0, 0, 0, 0, 0, 0, 0, 0, 0, 0, 0, 0, 0, 0, 0, 0, 0, 0, 0, 0, 164, 164, 0, 0, 0, 0, 0, 0, 0, 0, 0, 0, 0, 0, 0, 0, 0, 0, 0, 0, 0, 0, 0, 0, 0, 0, 0, 0, 0, 0, 0, 0, 0, 0, 0, 0, 0, 0, 0, 0, 164, 164, 164, 164, 164, 164, 164, 164, 164, 164, 164, 164, 164, 164, 164, 164, 164, 164, 164, 164, 164, 164, 164, 164, 164, 164, 164, 164, 164, 164, 164, 164, 164, 164, 164, 164, 164, 164, 164, 164, 164, 0, 0, 0, 0, 0, 0, 0, 0, 0, 0, 0, 0, 0, 0, 0, 0, 0, 0, 0, 0, 0, 0, 0, 0, 0, 0, 0, 0, 0, 0, 0, 0, 0, 0, 0, 0, 0, 0, 0, 0],
         "height":25,
         "name":"tile_sprinting",
         "opacity":1,
         "type":"tilelayer",
         "visible":false,
         "width":40,
         "x":0,
         "y":0
        }, 
        {
         "draworder":"topdown",
         "height":0,
         "name":"scene_sprinting",
         "objects":[],
         "opacity":1,
         "properties":
            {
             "#tile":"tile_sprinting",
             "foodStencil":"\"sprintingFood\"",
             "set":"{\"_\":[\"stencil\",\"stageModel\"]}",
             "stageComment":"\"Eat and run!\"",
             "stageName":"\"Sprinting\"",
             "startY":"21",
             "states":"{\n        \"name\":\"game\",\n        \"like\":[{\"_\":[\"stencil\",\"modelFoodKeeper\"]},{\"_\":[\"stencil\",\"modelSprinter\"]}]\n      }"
            },
         "type":"objectgroup",
         "visible":false,
         "width":0,
         "x":0,
         "y":0
        }, 
        {
         "data":[0, 0, 0, 0, 0, 0, 0, 0, 0, 0, 0, 0, 0, 0, 0, 0, 0, 0, 0, 0, 0, 0, 0, 0, 0, 0, 0, 0, 0, 0, 0, 0, 0, 0, 0, 0, 0, 0, 0, 0, 163, 163, 163, 163, 163, 163, 163, 163, 163, 163, 163, 163, 163, 163, 163, 163, 163, 163, 163, 163, 163, 163, 163, 163, 163, 163, 163, 163, 163, 163, 163, 163, 163, 163, 163, 163, 163, 163, 163, 163, 163, 0, 0, 0, 0, 0, 0, 0, 0, 0, 0, 0, 0, 0, 0, 0, 0, 0, 0, 0, 0, 0, 0, 0, 0, 0, 0, 0, 0, 0, 0, 163, 0, 0, 0, 0, 0, 0, 0, 163, 163, 0, 0, 0, 0, 0, 0, 0, 0, 0, 0, 0, 0, 0, 0, 0, 0, 0, 0, 0, 0, 0, 0, 0, 0, 0, 0, 0, 0, 0, 0, 163, 0, 0, 0, 0, 0, 0, 0, 163, 163, 0, 0, 0, 0, 0, 0, 0, 0, 0, 0, 0, 0, 0, 0, 0, 0, 0, 0, 0, 0, 0, 0, 0, 0, 0, 0, 0, 0, 0, 0, 163, 0, 0, 0, 0, 0, 0, 0, 163, 163, 0, 0, 0, 0, 0, 0, 0, 0, 0, 0, 0, 0, 0, 0, 0, 0, 0, 0, 0, 0, 0, 0, 0, 0, 0, 0, 0, 0, 0, 0, 163, 0, 0, 0, 0, 0, 0, 0, 163, 163, 0, 0, 0, 0, 0, 0, 0, 0, 0, 0, 0, 0, 0, 0, 0, 0, 0, 0, 0, 0, 0, 0, 0, 0, 0, 0, 0, 0, 0, 0, 163, 0, 0, 0, 0, 0, 0, 0, 163, 163, 0, 0, 0, 0, 0, 0, 0, 0, 0, 0, 0, 0, 0, 0, 0, 0, 0, 0, 0, 0, 0, 0, 0, 0, 0, 0, 0, 0, 0, 0, 163, 0, 0, 0, 0, 0, 0, 0, 163, 163, 0, 0, 0, 0, 0, 0, 0, 0, 0, 0, 0, 0, 0, 0, 0, 0, 0, 0, 0, 0, 0, 0, 0, 0, 0, 0, 0, 0, 0, 0, 163, 0, 0, 0, 0, 0, 0, 0, 163, 163, 0, 0, 0, 0, 0, 0, 0, 0, 0, 0, 0, 0, 0, 0, 0, 0, 0, 0, 0, 0, 0, 0, 0, 0, 0, 0, 0, 0, 0, 0, 163, 0, 0, 0, 0, 0, 0, 0, 163, 163, 0, 0, 0, 0, 0, 0, 0, 0, 0, 0, 0, 0, 0, 0, 0, 0, 0, 0, 0, 0, 0, 0, 0, 0, 0, 0, 0, 0, 0, 0, 163, 0, 0, 0, 0, 0, 0, 0, 163, 163, 0, 0, 0, 0, 0, 0, 0, 0, 0, 0, 0, 0, 0, 0, 0, 0, 0, 0, 0, 0, 0, 0, 0, 0, 0, 163, 163, 163, 163, 163, 163, 0, 0, 0, 0, 0, 0, 0, 163, 163, 0, 0, 0, 0, 0, 0, 0, 0, 0, 0, 0, 0, 0, 0, 0, 0, 0, 0, 0, 0, 0, 0, 0, 0, 0, 0, 0, 0, 0, 0, 0, 0, 0, 0, 0, 0, 0, 0, 163, 163, 0, 0, 0, 0, 0, 0, 0, 163, 163, 163, 163, 163, 163, 0, 0, 0, 0, 0, 0, 0, 0, 0, 0, 0, 0, 0, 0, 0, 0, 0, 0, 0, 0, 0, 0, 0, 0, 0, 163, 163, 0, 0, 0, 0, 0, 0, 0, 163, 0, 0, 0, 0, 0, 0, 0, 0, 0, 0, 0, 0, 0, 0, 0, 0, 0, 0, 0, 0, 0, 0, 0, 0, 0, 0, 0, 0, 0, 0, 163, 163, 0, 0, 0, 0, 0, 0, 0, 163, 0, 0, 0, 0, 0, 0, 0, 0, 0, 0, 0, 0, 0, 0, 0, 0, 0, 0, 0, 0, 0, 0, 0, 0, 0, 0, 0, 0, 0, 0, 163, 163, 0, 0, 0, 0, 0, 0, 0, 163, 0, 0, 0, 0, 0, 0, 0, 0, 0, 0, 0, 0, 0, 0, 0, 0, 0, 0, 0, 0, 0, 0, 0, 0, 0, 0, 0, 0, 0, 0, 163, 163, 0, 0, 0, 0, 0, 0, 0, 163, 0, 0, 0, 0, 0, 0, 0, 0, 0, 0, 0, 0, 0, 0, 0, 0, 0, 0, 0, 0, 0, 0, 0, 0, 0, 0, 0, 0, 0, 0, 163, 163, 0, 0, 0, 0, 0, 0, 0, 163, 0, 0, 0, 0, 0, 0, 0, 0, 0, 0, 0, 0, 0, 0, 0, 0, 0, 0, 0, 0, 0, 0, 0, 0, 0, 0, 0, 0, 0, 0, 163, 163, 0, 0, 0, 0, 0, 0, 0, 163, 0, 0, 0, 0, 0, 0, 0, 0, 0, 0, 0, 0, 0, 0, 0, 0, 0, 0, 0, 0, 0, 0, 0, 0, 0, 0, 0, 0, 0, 0, 163, 163, 0, 0, 0, 0, 0, 0, 0, 163, 0, 0, 0, 0, 0, 0, 0, 0, 0, 0, 0, 0, 0, 0, 0, 0, 0, 0, 0, 0, 0, 0, 0, 0, 0, 0, 0, 0, 0, 0, 163, 163, 0, 0, 0, 0, 0, 0, 0, 163, 0, 0, 0, 0, 0, 0, 0, 0, 0, 0, 0, 0, 0, 0, 0, 0, 0, 0, 0, 0, 0, 0, 0, 0, 0, 0, 0, 0, 0, 0, 163, 163, 0, 0, 0, 0, 0, 0, 0, 163, 0, 0, 0, 0, 0, 0, 0, 0, 0, 0, 0, 0, 0, 0, 0, 0, 0, 0, 0, 0, 0, 0, 0, 0, 0, 0, 0, 0, 0, 0, 163, 163, 163, 163, 163, 163, 163, 163, 163, 163, 163, 163, 163, 163, 163, 163, 163, 163, 163, 163, 163, 163, 163, 163, 163, 163, 163, 163, 163, 163, 163, 163, 163, 163, 163, 163, 163, 163, 163, 163, 163, 0, 0, 0, 0, 0, 0, 0, 0, 0, 0, 0, 0, 0, 0, 0, 0, 0, 0, 0, 0, 0, 0, 0, 0, 0, 0, 0, 0, 0, 0, 0, 0, 0, 0, 0, 0, 0, 0, 0, 0],
         "height":25,
         "name":"tile_bouncing",
         "opacity":1,
         "type":"tilelayer",
         "visible":false,
         "width":40,
         "x":0,
         "y":0
        }, 
        {
         "draworder":"topdown",
         "height":0,
         "name":"scene_bouncing",
         "objects":[],
         "opacity":1,
         "properties":
            {
             "#tile":"tile_bouncing",
             "foodStencil":"\"bouncingFood\"",
             "set":"{\"_\":[\"stencil\",\"stageModel\"]}",
             "stageComment":"\"Catch the food!\"",
             "stageName":"\"Bouncing\"",
             "states":"{\n        \"name\":\"game\",\n        \"like\":{\"_\":[\"stencil\",\"modelFoodKeeper\"]}\n      }"
            },
         "type":"objectgroup",
         "visible":false,
         "width":0,
         "x":0,
         "y":0
        }, 
        {
         "data":[0, 0, 0, 0, 0, 0, 0, 0, 0, 0, 0, 0, 0, 0, 0, 0, 0, 0, 0, 0, 0, 0, 0, 0, 0, 0, 0, 0, 0, 0, 0, 0, 0, 0, 0, 0, 0, 0, 0, 0, 162, 162, 162, 162, 162, 162, 162, 162, 162, 162, 162, 162, 162, 162, 162, 162, 162, 162, 162, 162, 162, 162, 162, 162, 162, 162, 162, 162, 162, 162, 162, 162, 162, 162, 162, 162, 162, 162, 162, 162, 162, 0, 0, 0, 0, 0, 0, 0, 0, 0, 0, 0, 0, 0, 0, 0, 0, 0, 0, 0, 0, 0, 0, 0, 0, 0, 0, 0, 0, 0, 0, 0, 0, 0, 0, 0, 0, 0, 0, 162, 162, 0, 0, 0, 0, 0, 0, 0, 0, 0, 0, 0, 0, 0, 0, 0, 0, 0, 0, 0, 0, 0, 0, 0, 0, 0, 0, 0, 0, 0, 0, 0, 0, 0, 0, 0, 0, 0, 0, 162, 162, 0, 0, 0, 0, 0, 0, 0, 0, 0, 0, 0, 0, 0, 0, 0, 0, 0, 0, 0, 0, 0, 0, 0, 0, 0, 0, 0, 0, 0, 0, 0, 0, 0, 0, 0, 0, 0, 0, 162, 162, 0, 0, 0, 0, 0, 0, 0, 0, 0, 0, 0, 0, 0, 0, 0, 0, 0, 0, 0, 0, 0, 0, 0, 0, 0, 0, 0, 0, 0, 0, 0, 0, 0, 0, 0, 0, 0, 0, 162, 162, 0, 0, 0, 0, 0, 0, 0, 0, 0, 0, 0, 0, 0, 0, 0, 0, 0, 0, 0, 0, 0, 0, 0, 0, 0, 0, 0, 0, 0, 0, 0, 0, 0, 0, 0, 0, 0, 0, 162, 162, 0, 0, 0, 0, 0, 0, 0, 0, 0, 0, 0, 0, 0, 0, 0, 0, 0, 0, 0, 0, 0, 0, 0, 0, 0, 0, 0, 0, 0, 0, 0, 0, 0, 0, 0, 0, 0, 0, 162, 162, 0, 0, 0, 0, 162, 162, 162, 162, 162, 162, 162, 162, 162, 162, 162, 162, 162, 162, 162, 162, 162, 162, 162, 162, 162, 162, 162, 162, 162, 162, 162, 162, 162, 0, 0, 0, 0, 0, 162, 162, 0, 0, 0, 0, 0, 0, 0, 0, 0, 0, 0, 0, 0, 0, 0, 0, 0, 0, 0, 0, 0, 0, 0, 0, 0, 0, 0, 0, 0, 0, 0, 0, 0, 0, 0, 0, 0, 0, 162, 162, 0, 0, 0, 0, 0, 0, 0, 0, 0, 0, 0, 0, 0, 0, 0, 0, 0, 0, 0, 0, 0, 0, 0, 0, 0, 0, 0, 0, 0, 0, 0, 0, 0, 0, 0, 0, 0, 0, 162, 162, 0, 0, 0, 0, 0, 0, 0, 0, 0, 0, 0, 0, 0, 0, 0, 0, 0, 0, 0, 0, 0, 0, 0, 0, 0, 0, 0, 0, 0, 0, 0, 0, 0, 0, 0, 0, 0, 0, 162, 162, 0, 0, 0, 0, 0, 0, 0, 0, 0, 0, 0, 0, 0, 0, 0, 0, 0, 0, 0, 0, 0, 0, 0, 0, 0, 0, 0, 0, 0, 0, 0, 0, 0, 0, 0, 0, 0, 0, 162, 162, 0, 0, 0, 0, 0, 0, 0, 0, 0, 0, 0, 0, 0, 0, 0, 0, 0, 0, 0, 0, 0, 0, 0, 0, 0, 0, 0, 0, 0, 0, 0, 0, 0, 0, 0, 0, 0, 0, 162, 162, 0, 0, 0, 0, 0, 0, 0, 0, 0, 0, 0, 0, 0, 0, 0, 0, 0, 0, 0, 0, 0, 0, 0, 0, 0, 0, 0, 0, 0, 0, 0, 0, 0, 0, 0, 0, 0, 0, 162, 162, 0, 0, 0, 0, 0, 0, 0, 0, 0, 0, 0, 0, 0, 0, 0, 0, 0, 0, 0, 0, 0, 0, 0, 0, 0, 0, 0, 0, 0, 0, 0, 0, 0, 0, 0, 0, 0, 0, 162, 162, 0, 0, 0, 0, 162, 162, 162, 162, 162, 162, 162, 162, 162, 162, 162, 162, 162, 162, 162, 162, 162, 162, 162, 162, 162, 162, 162, 162, 162, 162, 162, 162, 162, 0, 0, 0, 0, 0, 162, 162, 0, 0, 0, 0, 0, 0, 0, 0, 0, 0, 0, 0, 0, 0, 0, 0, 0, 0, 0, 0, 0, 0, 0, 0, 0, 0, 0, 0, 0, 0, 0, 0, 0, 0, 0, 0, 0, 0, 162, 162, 0, 0, 0, 0, 0, 0, 0, 0, 0, 0, 0, 0, 0, 0, 0, 0, 0, 0, 0, 0, 0, 0, 0, 0, 0, 0, 0, 0, 0, 0, 0, 0, 0, 0, 0, 0, 0, 0, 162, 162, 0, 0, 0, 0, 0, 0, 0, 0, 0, 0, 0, 0, 0, 0, 0, 0, 0, 0, 0, 0, 0, 0, 0, 0, 0, 0, 0, 0, 0, 0, 0, 0, 0, 0, 0, 0, 0, 0, 162, 162, 0, 0, 0, 0, 0, 0, 0, 0, 0, 0, 0, 0, 0, 0, 0, 0, 0, 0, 0, 0, 0, 0, 0, 0, 0, 0, 0, 0, 0, 0, 0, 0, 0, 0, 0, 0, 0, 0, 162, 162, 0, 0, 0, 0, 0, 0, 0, 0, 0, 0, 0, 0, 0, 0, 0, 0, 0, 0, 0, 0, 0, 0, 0, 0, 0, 0, 0, 0, 0, 0, 0, 0, 0, 0, 0, 0, 0, 0, 162, 162, 0, 0, 0, 0, 0, 0, 0, 0, 0, 0, 0, 0, 0, 0, 0, 0, 0, 0, 0, 0, 0, 0, 0, 0, 0, 0, 0, 0, 0, 0, 0, 0, 0, 0, 0, 0, 0, 0, 162, 162, 162, 162, 162, 162, 162, 162, 162, 162, 162, 162, 162, 162, 162, 162, 162, 162, 162, 162, 162, 162, 162, 162, 162, 162, 162, 162, 162, 162, 162, 162, 162, 162, 162, 162, 162, 162, 162, 162, 162, 0, 0, 0, 0, 0, 0, 0, 0, 0, 0, 0, 0, 0, 0, 0, 0, 0, 0, 0, 0, 0, 0, 0, 0, 0, 0, 0, 0, 0, 0, 0, 0, 0, 0, 0, 0, 0, 0, 0, 0],
         "height":25,
         "name":"tile_blockade",
         "opacity":1,
         "type":"tilelayer",
         "visible":false,
         "width":40,
         "x":0,
         "y":0
        }, 
        {
         "draworder":"topdown",
         "height":0,
         "name":"scene_blockade",
         "objects":[],
         "opacity":1,
         "properties":
            {
             "#tile":"tile_blockade",
             "backgroundTileX":"8",
             "set":"{\"_\":[\"stencil\",\"stageModel\"]}",
             "snakeTileY":"8",
             "stageComment":"\"Unlimited growth!\"",
             "stageName":"\"Blockade\"",
             "startSnakeFood":"99999",
             "targetLength":"200"
            },
         "type":"objectgroup",
         "visible":false,
         "width":0,
         "x":0,
         "y":0
        }, 
        {
         "draworder":"topdown",
         "height":0,
         "name":"scene_10",
         "objects":[],
         "opacity":1,
         "properties":
            {
             "#tile":"tile_10",
             "set":"{\"_\":[\"stencil\",\"stageModel\"]}",
             "stageName":"\"Double U\"",
             "startY":"4",
             "states":"{ \"name\":\"game\", \"like\":{ \"_\":[ \"stencil\", \"modelFoodKeeper\" ] } }"
            },
         "type":"objectgroup",
         "visible":false,
         "width":0,
         "x":0,
         "y":0
        }, 
        {
         "data":[0, 0, 0, 0, 0, 0, 0, 0, 0, 0, 0, 0, 0, 0, 0, 0, 0, 0, 0, 0, 0, 0, 0, 0, 0, 0, 0, 0, 0, 0, 0, 0, 0, 0, 0, 0, 0, 0, 0, 0, 161, 161, 161, 161, 161, 161, 161, 161, 161, 161, 161, 161, 161, 161, 161, 161, 161, 161, 161, 161, 161, 161, 161, 161, 161, 161, 161, 161, 161, 161, 161, 161, 161, 161, 161, 161, 161, 161, 161, 161, 161, 0, 0, 0, 0, 0, 0, 0, 0, 0, 0, 0, 0, 0, 0, 0, 0, 0, 0, 0, 0, 0, 0, 0, 0, 0, 0, 0, 0, 0, 0, 0, 0, 0, 0, 0, 0, 0, 0, 161, 161, 0, 0, 0, 0, 0, 0, 0, 0, 0, 0, 0, 0, 0, 0, 0, 0, 0, 0, 0, 0, 0, 0, 0, 0, 0, 0, 0, 0, 0, 0, 0, 0, 0, 0, 0, 0, 0, 0, 161, 161, 0, 0, 0, 0, 0, 0, 0, 0, 0, 0, 0, 0, 0, 0, 0, 0, 0, 0, 0, 0, 0, 0, 0, 0, 0, 0, 0, 0, 0, 0, 0, 0, 0, 0, 0, 0, 0, 0, 161, 161, 0, 0, 0, 0, 0, 0, 0, 0, 0, 0, 0, 0, 0, 0, 0, 0, 0, 0, 0, 0, 0, 0, 0, 0, 0, 0, 0, 0, 0, 0, 0, 0, 0, 0, 0, 0, 0, 0, 161, 161, 0, 0, 0, 0, 161, 0, 0, 0, 0, 161, 161, 161, 161, 161, 161, 161, 161, 161, 161, 161, 161, 161, 161, 161, 161, 161, 161, 161, 161, 0, 0, 0, 0, 161, 0, 0, 0, 0, 161, 161, 0, 0, 0, 0, 161, 0, 0, 0, 0, 161, 0, 0, 0, 0, 0, 0, 0, 0, 0, 0, 0, 0, 0, 0, 0, 0, 0, 0, 161, 0, 0, 0, 0, 161, 0, 0, 0, 0, 161, 161, 0, 0, 0, 0, 161, 0, 0, 0, 0, 161, 0, 0, 0, 0, 0, 0, 0, 0, 0, 0, 0, 0, 0, 0, 0, 0, 0, 0, 161, 0, 0, 0, 0, 161, 0, 0, 0, 0, 161, 161, 0, 0, 0, 0, 161, 0, 0, 0, 0, 161, 0, 0, 0, 0, 0, 0, 0, 0, 0, 0, 0, 0, 0, 0, 0, 0, 0, 0, 161, 0, 0, 0, 0, 161, 0, 0, 0, 0, 161, 161, 0, 0, 0, 0, 161, 0, 0, 0, 0, 161, 0, 0, 0, 0, 0, 0, 0, 0, 0, 0, 0, 0, 0, 0, 0, 0, 0, 0, 161, 0, 0, 0, 0, 161, 0, 0, 0, 0, 161, 161, 0, 0, 0, 0, 161, 0, 0, 0, 0, 161, 0, 0, 0, 0, 0, 0, 0, 0, 0, 0, 0, 0, 0, 0, 0, 0, 0, 0, 161, 0, 0, 0, 0, 161, 0, 0, 0, 0, 161, 161, 0, 0, 0, 0, 161, 0, 0, 0, 0, 161, 0, 0, 0, 0, 0, 0, 0, 0, 0, 0, 0, 0, 0, 0, 0, 0, 0, 0, 161, 0, 0, 0, 0, 161, 0, 0, 0, 0, 161, 161, 0, 0, 0, 0, 161, 0, 0, 0, 0, 161, 0, 0, 0, 0, 0, 0, 0, 0, 0, 0, 0, 0, 0, 0, 0, 0, 0, 0, 161, 0, 0, 0, 0, 161, 0, 0, 0, 0, 161, 161, 0, 0, 0, 0, 161, 0, 0, 0, 0, 0, 0, 0, 0, 0, 0, 0, 0, 0, 0, 0, 0, 0, 0, 0, 0, 0, 0, 0, 0, 0, 0, 0, 0, 161, 0, 0, 0, 0, 161, 161, 0, 0, 0, 0, 161, 0, 0, 0, 0, 0, 0, 0, 0, 0, 0, 0, 0, 0, 0, 0, 0, 0, 0, 0, 0, 0, 0, 0, 0, 0, 0, 0, 0, 161, 0, 0, 0, 0, 161, 161, 0, 0, 0, 0, 161, 0, 0, 0, 0, 0, 0, 0, 0, 0, 0, 0, 0, 0, 0, 0, 0, 0, 0, 0, 0, 0, 0, 0, 0, 0, 0, 0, 0, 161, 0, 0, 0, 0, 161, 161, 0, 0, 0, 0, 161, 0, 0, 0, 0, 0, 0, 0, 0, 0, 0, 0, 0, 0, 0, 0, 0, 0, 0, 0, 0, 0, 0, 0, 0, 0, 0, 0, 0, 161, 0, 0, 0, 0, 161, 161, 0, 0, 0, 0, 161, 161, 161, 161, 161, 161, 161, 161, 161, 161, 161, 161, 161, 161, 161, 161, 161, 161, 161, 161, 161, 161, 161, 161, 161, 161, 161, 161, 161, 161, 0, 0, 0, 0, 161, 161, 0, 0, 0, 0, 0, 0, 0, 0, 0, 0, 0, 0, 0, 0, 0, 0, 0, 0, 0, 0, 0, 0, 0, 0, 0, 0, 0, 0, 0, 0, 0, 0, 0, 0, 0, 0, 0, 0, 161, 161, 0, 0, 0, 0, 0, 0, 0, 0, 0, 0, 0, 0, 0, 0, 0, 0, 0, 0, 0, 0, 0, 0, 0, 0, 0, 0, 0, 0, 0, 0, 0, 0, 0, 0, 0, 0, 0, 0, 161, 161, 0, 0, 0, 0, 0, 0, 0, 0, 0, 0, 0, 0, 0, 0, 0, 0, 0, 0, 0, 0, 0, 0, 0, 0, 0, 0, 0, 0, 0, 0, 0, 0, 0, 0, 0, 0, 0, 0, 161, 161, 0, 0, 0, 0, 0, 0, 0, 0, 0, 0, 0, 0, 0, 0, 0, 0, 0, 0, 0, 0, 0, 0, 0, 0, 0, 0, 0, 0, 0, 0, 0, 0, 0, 0, 0, 0, 0, 0, 161, 161, 161, 161, 161, 161, 161, 161, 161, 161, 161, 161, 161, 161, 161, 161, 161, 161, 161, 161, 161, 161, 161, 161, 161, 161, 161, 161, 161, 161, 161, 161, 161, 161, 161, 161, 161, 161, 161, 161, 161, 0, 0, 0, 0, 0, 0, 0, 0, 0, 0, 0, 0, 0, 0, 0, 0, 0, 0, 0, 0, 0, 0, 0, 0, 0, 0, 0, 0, 0, 0, 0, 0, 0, 0, 0, 0, 0, 0, 0, 0],
         "height":25,
         "name":"tile_10",
         "opacity":1,
         "type":"tilelayer",
         "visible":true,
         "width":40,
         "x":0,
         "y":0
        }, 
        {
         "draworder":"topdown",
         "height":0,
         "name":"scene_9",
         "objects":[],
         "opacity":1,
         "properties":
            {
             "#tile":"tile_9",
             "set":"{\"_\":[\"stencil\",\"stageModel\"]}",
             "stageName":"\"Table\"",
             "startY":"5",
             "states":"{ \"name\":\"game\", \"like\":{ \"_\":[ \"stencil\", \"modelFoodKeeper\" ] } }"
            },
         "type":"objectgroup",
         "visible":false,
         "width":0,
         "x":0,
         "y":0
        }, 
        {
         "data":[0, 0, 0, 0, 0, 0, 0, 0, 0, 0, 0, 0, 0, 0, 0, 0, 0, 0, 0, 0, 0, 0, 0, 0, 0, 0, 0, 0, 0, 0, 0, 0, 0, 0, 0, 0, 0, 0, 0, 0, 0, 0, 0, 0, 0, 0, 0, 0, 0, 0, 0, 0, 0, 0, 0, 0, 0, 0, 0, 0, 0, 0, 0, 0, 0, 0, 0, 0, 0, 0, 0, 0, 0, 0, 0, 0, 0, 0, 0, 0, 0, 0, 0, 0, 0, 0, 0, 0, 0, 0, 0, 0, 0, 0, 0, 0, 0, 0, 0, 0, 0, 0, 0, 0, 0, 0, 0, 0, 0, 0, 0, 0, 0, 0, 0, 0, 0, 0, 0, 0, 0, 0, 0, 0, 0, 0, 0, 0, 0, 0, 0, 0, 0, 0, 0, 0, 0, 0, 0, 0, 0, 0, 0, 0, 0, 0, 0, 0, 0, 0, 0, 0, 0, 0, 0, 0, 0, 0, 0, 0, 0, 0, 0, 0, 0, 0, 0, 0, 0, 0, 0, 0, 0, 0, 0, 0, 0, 0, 0, 0, 0, 0, 0, 0, 0, 0, 0, 0, 0, 0, 0, 0, 0, 0, 0, 0, 0, 0, 0, 0, 0, 0, 0, 0, 0, 0, 0, 0, 0, 0, 0, 0, 0, 0, 0, 0, 0, 0, 0, 0, 0, 0, 0, 0, 0, 0, 0, 0, 0, 0, 0, 0, 0, 0, 0, 0, 0, 0, 0, 0, 0, 0, 0, 0, 0, 0, 0, 0, 0, 0, 0, 0, 0, 0, 0, 0, 0, 0, 0, 0, 0, 0, 0, 0, 0, 0, 0, 0, 0, 0, 0, 0, 0, 0, 0, 0, 0, 0, 0, 0, 0, 0, 0, 0, 0, 0, 0, 0, 0, 0, 0, 0, 0, 0, 0, 0, 0, 0, 0, 0, 0, 0, 0, 0, 0, 0, 0, 0, 0, 0, 0, 0, 0, 0, 0, 0, 0, 0, 0, 0, 0, 0, 0, 0, 0, 0, 0, 0, 0, 0, 0, 0, 0, 0, 0, 0, 0, 0, 0, 0, 0, 0, 0, 0, 0, 0, 0, 0, 0, 0, 0, 0, 0, 0, 0, 0, 0, 0, 0, 0, 0, 0, 0, 0, 0, 0, 0, 0, 0, 0, 0, 0, 0, 0, 0, 0, 0, 0, 0, 0, 0, 0, 0, 0, 0, 0, 0, 0, 0, 0, 0, 0, 0, 0, 0, 0, 0, 0, 0, 0, 0, 0, 0, 0, 0, 0, 0, 0, 0, 0, 0, 0, 0, 0, 0, 0, 0, 0, 0, 0, 0, 0, 0, 0, 0, 0, 0, 0, 0, 0, 0, 0, 0, 0, 0, 0, 0, 0, 0, 0, 0, 0, 0, 0, 0, 0, 0, 0, 0, 0, 0, 0, 0, 0, 0, 0, 0, 0, 0, 0, 0, 0, 0, 0, 0, 0, 0, 0, 0, 0, 0, 0, 0, 0, 0, 0, 0, 0, 0, 0, 161, 161, 161, 161, 161, 161, 161, 161, 161, 161, 161, 161, 161, 161, 161, 161, 161, 161, 161, 161, 161, 161, 161, 161, 161, 161, 161, 161, 161, 161, 161, 161, 161, 161, 161, 161, 161, 161, 161, 161, 0, 0, 0, 0, 0, 0, 0, 161, 0, 0, 0, 0, 0, 0, 0, 0, 0, 0, 0, 0, 0, 0, 0, 0, 0, 0, 0, 0, 0, 0, 0, 0, 161, 0, 0, 0, 0, 0, 0, 0, 0, 0, 0, 0, 0, 0, 0, 161, 0, 0, 0, 0, 0, 0, 0, 0, 0, 0, 0, 0, 0, 0, 0, 0, 0, 0, 0, 0, 0, 0, 0, 0, 161, 0, 0, 0, 0, 0, 0, 0, 0, 0, 0, 0, 0, 0, 0, 161, 0, 0, 0, 0, 0, 0, 0, 0, 0, 0, 0, 0, 0, 0, 0, 0, 0, 0, 0, 0, 0, 0, 0, 0, 161, 0, 0, 0, 0, 0, 0, 0, 0, 0, 0, 0, 0, 0, 0, 161, 0, 0, 0, 0, 0, 0, 0, 0, 0, 0, 0, 0, 0, 0, 0, 0, 0, 0, 0, 0, 0, 0, 0, 0, 161, 0, 0, 0, 0, 0, 0, 0, 0, 0, 0, 0, 0, 0, 0, 161, 0, 0, 0, 0, 0, 0, 0, 0, 0, 0, 0, 0, 0, 0, 0, 0, 0, 0, 0, 0, 0, 0, 0, 0, 161, 0, 0, 0, 0, 0, 0, 0, 0, 0, 0, 0, 0, 0, 0, 161, 0, 0, 0, 0, 0, 0, 0, 0, 0, 0, 0, 0, 0, 0, 0, 0, 0, 0, 0, 0, 0, 0, 0, 0, 161, 0, 0, 0, 0, 0, 0, 0, 0, 0, 0, 0, 0, 0, 0, 161, 0, 0, 0, 0, 0, 0, 0, 0, 0, 0, 0, 0, 0, 0, 0, 0, 0, 0, 0, 0, 0, 0, 0, 0, 161, 0, 0, 0, 0, 0, 0, 0, 0, 0, 0, 0, 0, 0, 0, 161, 0, 0, 0, 0, 0, 0, 0, 0, 0, 0, 0, 0, 0, 0, 0, 0, 0, 0, 0, 0, 0, 0, 0, 0, 161, 0, 0, 0, 0, 0, 0, 0, 0, 0, 0, 0, 0, 0, 0, 161, 0, 0, 0, 0, 0, 0, 0, 0, 0, 0, 0, 0, 0, 0, 0, 0, 0, 0, 0, 0, 0, 0, 0, 0, 161, 0, 0, 0, 0, 0, 0, 0, 0, 0, 0, 0, 0, 0, 0, 161, 0, 0, 0, 0, 0, 0, 0, 0, 0, 0, 0, 0, 0, 0, 0, 0, 0, 0, 0, 0, 0, 0, 0, 0, 161, 0, 0, 0, 0, 0, 0, 0, 0, 0, 0, 0, 0, 0, 0, 161, 0, 0, 0, 0, 0, 0, 0, 0, 0, 0, 0, 0, 0, 0, 0, 0, 0, 0, 0, 0, 0, 0, 0, 0, 161, 0, 0, 0, 0, 0, 0, 0, 0, 0, 0, 0, 0, 0, 0, 0, 0, 0, 0, 0, 0, 0, 0, 0, 0, 0, 0, 0, 0, 0, 0, 0, 0, 0, 0, 0, 0, 0, 0, 0, 0, 0, 0, 0, 0, 0, 0, 0],
         "height":25,
         "name":"tile_9",
         "opacity":1,
         "type":"tilelayer",
         "visible":false,
         "width":40,
         "x":0,
         "y":0
        }, 
        {
         "draworder":"topdown",
         "height":0,
         "name":"scene_8",
         "objects":[],
         "opacity":1,
         "properties":
            {
             "#tile":"tile_8",
             "set":"{\"_\":[\"stencil\",\"stageModel\"]}",
             "stageName":"\"Cross\"",
             "startX":"14",
             "startY":"15",
             "states":"{ \"name\":\"game\", \"like\":{ \"_\":[ \"stencil\", \"modelFoodKeeper\" ] } }"
            },
         "type":"objectgroup",
         "visible":false,
         "width":0,
         "x":0,
         "y":0
        }, 
        {
         "data":[0, 0, 0, 0, 0, 0, 0, 0, 0, 0, 0, 0, 0, 0, 0, 0, 0, 0, 0, 0, 0, 0, 0, 0, 0, 0, 0, 0, 0, 0, 0, 0, 0, 0, 0, 0, 0, 0, 0, 0, 0, 0, 0, 0, 0, 0, 0, 0, 0, 0, 0, 0, 0, 0, 0, 0, 0, 0, 0, 0, 161, 0, 0, 0, 0, 0, 0, 0, 0, 0, 0, 0, 0, 0, 0, 0, 0, 0, 0, 0, 0, 0, 0, 0, 0, 0, 0, 0, 0, 0, 0, 0, 0, 0, 0, 0, 0, 0, 0, 0, 161, 0, 0, 0, 0, 0, 0, 0, 0, 0, 0, 0, 0, 0, 0, 0, 0, 0, 0, 0, 0, 0, 0, 0, 0, 0, 0, 0, 0, 0, 0, 0, 0, 0, 0, 0, 0, 0, 0, 0, 161, 0, 0, 0, 0, 0, 0, 0, 0, 0, 0, 0, 0, 0, 0, 0, 0, 0, 0, 0, 0, 0, 0, 0, 0, 0, 0, 0, 0, 0, 0, 0, 0, 0, 0, 0, 0, 0, 0, 0, 161, 0, 0, 0, 0, 0, 0, 0, 0, 0, 0, 0, 0, 0, 0, 0, 0, 0, 0, 0, 0, 0, 0, 0, 0, 0, 0, 0, 0, 0, 0, 0, 0, 0, 0, 0, 0, 0, 0, 0, 161, 0, 0, 0, 0, 0, 0, 0, 0, 0, 0, 0, 0, 0, 0, 0, 0, 0, 0, 0, 0, 0, 0, 0, 0, 0, 0, 0, 0, 0, 0, 0, 0, 0, 0, 0, 0, 0, 0, 0, 161, 0, 0, 0, 0, 0, 0, 0, 0, 0, 0, 0, 0, 0, 0, 0, 0, 0, 0, 0, 0, 0, 0, 0, 0, 0, 0, 0, 0, 0, 0, 0, 0, 0, 0, 0, 0, 0, 0, 0, 161, 0, 0, 0, 0, 0, 0, 0, 0, 0, 0, 0, 0, 0, 0, 0, 0, 0, 0, 0, 0, 0, 0, 0, 0, 0, 0, 0, 0, 0, 0, 0, 0, 0, 0, 0, 0, 0, 0, 0, 161, 0, 0, 0, 0, 0, 0, 0, 0, 0, 0, 0, 0, 0, 0, 0, 0, 0, 0, 0, 0, 0, 0, 0, 0, 0, 0, 0, 0, 0, 0, 0, 0, 0, 0, 0, 0, 0, 0, 0, 161, 0, 0, 0, 0, 0, 0, 0, 0, 0, 0, 0, 0, 0, 0, 0, 0, 0, 0, 0, 0, 0, 0, 0, 0, 0, 0, 0, 0, 0, 0, 0, 0, 0, 0, 0, 0, 0, 0, 0, 161, 0, 0, 0, 0, 0, 0, 0, 0, 0, 0, 0, 0, 0, 0, 0, 0, 0, 0, 0, 0, 0, 0, 0, 0, 0, 0, 0, 0, 0, 0, 0, 0, 0, 0, 0, 0, 0, 0, 0, 161, 0, 0, 0, 0, 0, 0, 0, 0, 0, 0, 0, 0, 0, 0, 0, 0, 0, 0, 0, 161, 161, 161, 161, 161, 161, 161, 161, 161, 161, 161, 161, 161, 161, 161, 161, 161, 161, 161, 161, 161, 161, 161, 161, 161, 161, 161, 161, 161, 161, 161, 161, 161, 161, 161, 161, 161, 161, 161, 161, 0, 0, 0, 0, 0, 0, 0, 0, 0, 0, 0, 0, 0, 0, 0, 0, 0, 0, 0, 0, 161, 0, 0, 0, 0, 0, 0, 0, 0, 0, 0, 0, 0, 0, 0, 0, 0, 0, 0, 0, 0, 0, 0, 0, 0, 0, 0, 0, 0, 0, 0, 0, 0, 0, 0, 0, 0, 0, 0, 0, 161, 0, 0, 0, 0, 0, 0, 0, 0, 0, 0, 0, 0, 0, 0, 0, 0, 0, 0, 0, 0, 0, 0, 0, 0, 0, 0, 0, 0, 0, 0, 0, 0, 0, 0, 0, 0, 0, 0, 0, 161, 0, 0, 0, 0, 0, 0, 0, 0, 0, 0, 0, 0, 0, 0, 0, 0, 0, 0, 0, 0, 0, 0, 0, 0, 0, 0, 0, 0, 0, 0, 0, 0, 0, 0, 0, 0, 0, 0, 0, 161, 0, 0, 0, 0, 0, 0, 0, 0, 0, 0, 0, 0, 0, 0, 0, 0, 0, 0, 0, 0, 0, 0, 0, 0, 0, 0, 0, 0, 0, 0, 0, 0, 0, 0, 0, 0, 0, 0, 0, 161, 0, 0, 0, 0, 0, 0, 0, 0, 0, 0, 0, 0, 0, 0, 0, 0, 0, 0, 0, 0, 0, 0, 0, 0, 0, 0, 0, 0, 0, 0, 0, 0, 0, 0, 0, 0, 0, 0, 0, 161, 0, 0, 0, 0, 0, 0, 0, 0, 0, 0, 0, 0, 0, 0, 0, 0, 0, 0, 0, 0, 0, 0, 0, 0, 0, 0, 0, 0, 0, 0, 0, 0, 0, 0, 0, 0, 0, 0, 0, 161, 0, 0, 0, 0, 0, 0, 0, 0, 0, 0, 0, 0, 0, 0, 0, 0, 0, 0, 0, 0, 0, 0, 0, 0, 0, 0, 0, 0, 0, 0, 0, 0, 0, 0, 0, 0, 0, 0, 0, 161, 0, 0, 0, 0, 0, 0, 0, 0, 0, 0, 0, 0, 0, 0, 0, 0, 0, 0, 0, 0, 0, 0, 0, 0, 0, 0, 0, 0, 0, 0, 0, 0, 0, 0, 0, 0, 0, 0, 0, 161, 0, 0, 0, 0, 0, 0, 0, 0, 0, 0, 0, 0, 0, 0, 0, 0, 0, 0, 0, 0, 0, 0, 0, 0, 0, 0, 0, 0, 0, 0, 0, 0, 0, 0, 0, 0, 0, 0, 0, 161, 0, 0, 0, 0, 0, 0, 0, 0, 0, 0, 0, 0, 0, 0, 0, 0, 0, 0, 0, 0, 0, 0, 0, 0, 0, 0, 0, 0, 0, 0, 0, 0, 0, 0, 0, 0, 0, 0, 0, 161, 0, 0, 0, 0, 0, 0, 0, 0, 0, 0, 0, 0, 0, 0, 0, 0, 0, 0, 0, 0, 0, 0, 0, 0, 0, 0, 0, 0, 0, 0, 0, 0, 0, 0, 0, 0, 0, 0, 0, 0, 0, 0, 0, 0, 0, 0, 0, 0, 0, 0, 0, 0, 0, 0, 0, 0, 0, 0, 0],
         "height":25,
         "name":"tile_8",
         "opacity":1,
         "type":"tilelayer",
         "visible":false,
         "width":40,
         "x":0,
         "y":0
        }, 
        {
         "draworder":"topdown",
         "height":0,
         "name":"scene_7",
         "objects":[],
         "opacity":1,
         "properties":
            {
             "#tile":"tile_7",
             "set":"{\"_\":[\"stencil\",\"stageModel\"]}",
             "stageName":"\"A-Maze\"",
             "states":"{ \"name\":\"game\", \"like\":{ \"_\":[ \"stencil\", \"modelFoodKeeper\" ] } }"
            },
         "type":"objectgroup",
         "visible":false,
         "width":0,
         "x":0,
         "y":0
        }, 
        {
         "data":[0, 0, 0, 0, 0, 0, 0, 0, 0, 0, 0, 0, 0, 0, 0, 0, 0, 0, 0, 0, 0, 0, 0, 0, 0, 0, 0, 0, 0, 0, 0, 0, 0, 0, 0, 0, 0, 0, 0, 0, 161, 161, 161, 161, 161, 0, 0, 0, 0, 161, 161, 161, 161, 161, 161, 161, 161, 161, 161, 161, 161, 161, 161, 161, 161, 161, 161, 161, 161, 161, 161, 161, 161, 161, 161, 161, 0, 0, 0, 0, 161, 0, 0, 0, 0, 0, 0, 0, 0, 0, 0, 0, 0, 161, 0, 0, 0, 0, 0, 0, 0, 0, 0, 0, 0, 0, 0, 0, 0, 0, 0, 0, 0, 0, 0, 0, 0, 0, 0, 0, 161, 0, 0, 0, 0, 0, 0, 0, 0, 0, 0, 0, 0, 161, 0, 0, 0, 0, 0, 0, 0, 0, 0, 0, 0, 0, 0, 0, 0, 0, 0, 0, 0, 0, 0, 0, 0, 0, 0, 0, 161, 0, 0, 0, 0, 0, 0, 0, 0, 0, 0, 0, 0, 161, 0, 0, 0, 0, 0, 0, 0, 0, 0, 0, 0, 0, 0, 0, 0, 0, 0, 0, 0, 0, 0, 0, 0, 0, 0, 0, 0, 0, 0, 0, 0, 0, 0, 0, 0, 0, 0, 0, 0, 161, 0, 0, 0, 0, 0, 0, 0, 0, 0, 0, 0, 0, 0, 0, 0, 0, 0, 0, 0, 0, 0, 0, 0, 0, 0, 0, 0, 0, 0, 0, 0, 0, 0, 0, 0, 0, 0, 0, 0, 161, 0, 0, 0, 0, 0, 0, 0, 0, 0, 0, 0, 0, 0, 0, 0, 0, 0, 0, 0, 0, 0, 0, 0, 0, 0, 0, 0, 0, 0, 0, 0, 0, 0, 0, 0, 0, 0, 0, 0, 161, 0, 0, 0, 0, 0, 0, 0, 0, 0, 0, 0, 0, 0, 0, 0, 0, 0, 0, 0, 0, 0, 0, 0, 0, 0, 0, 0, 0, 0, 0, 0, 0, 0, 0, 0, 0, 0, 0, 0, 161, 0, 0, 0, 0, 0, 0, 0, 0, 0, 0, 0, 0, 0, 0, 0, 0, 0, 0, 0, 0, 0, 0, 0, 0, 0, 0, 161, 161, 161, 161, 161, 161, 161, 161, 161, 161, 161, 161, 161, 161, 0, 0, 0, 0, 161, 161, 161, 161, 161, 161, 161, 161, 161, 161, 161, 161, 161, 161, 161, 161, 161, 161, 161, 161, 161, 161, 0, 0, 0, 0, 0, 0, 0, 0, 0, 0, 0, 0, 0, 0, 0, 0, 0, 0, 0, 0, 0, 0, 0, 0, 0, 0, 0, 0, 0, 0, 0, 0, 0, 0, 0, 0, 0, 0, 0, 0, 0, 0, 0, 0, 0, 0, 0, 0, 0, 0, 0, 0, 0, 0, 0, 0, 0, 0, 0, 0, 0, 0, 0, 0, 0, 0, 0, 0, 0, 0, 0, 0, 0, 0, 0, 0, 0, 0, 0, 0, 0, 0, 0, 0, 0, 0, 0, 0, 0, 0, 0, 0, 0, 0, 0, 0, 0, 0, 0, 0, 0, 0, 0, 0, 0, 0, 0, 0, 0, 0, 0, 0, 0, 0, 0, 0, 0, 0, 0, 0, 0, 0, 0, 0, 0, 0, 0, 0, 0, 0, 0, 0, 0, 0, 0, 0, 0, 0, 0, 0, 0, 0, 0, 0, 0, 0, 0, 0, 0, 0, 0, 0, 0, 0, 0, 0, 0, 0, 0, 0, 0, 0, 0, 0, 0, 0, 0, 0, 0, 0, 0, 0, 0, 0, 0, 0, 0, 0, 0, 0, 0, 0, 0, 0, 0, 0, 0, 0, 0, 0, 0, 0, 0, 0, 0, 0, 0, 0, 0, 0, 0, 0, 0, 0, 0, 0, 0, 0, 0, 0, 0, 0, 0, 0, 0, 0, 0, 0, 0, 0, 0, 0, 0, 0, 0, 0, 0, 0, 0, 0, 0, 0, 0, 0, 0, 0, 0, 0, 0, 0, 0, 0, 0, 0, 0, 0, 0, 0, 0, 0, 0, 0, 0, 0, 0, 0, 0, 0, 0, 0, 0, 0, 0, 0, 0, 0, 0, 0, 0, 0, 0, 0, 0, 0, 0, 0, 0, 0, 0, 0, 161, 161, 161, 161, 161, 161, 161, 161, 161, 161, 161, 161, 161, 161, 161, 161, 161, 161, 161, 161, 161, 161, 161, 161, 161, 161, 161, 161, 161, 161, 161, 161, 161, 161, 161, 161, 161, 161, 161, 161, 0, 0, 0, 0, 0, 0, 0, 0, 0, 0, 0, 0, 0, 0, 0, 0, 0, 0, 0, 0, 0, 0, 161, 0, 0, 0, 0, 0, 0, 0, 0, 0, 0, 0, 0, 0, 0, 0, 0, 0, 0, 0, 0, 0, 0, 0, 0, 0, 0, 0, 0, 0, 0, 0, 0, 0, 0, 0, 0, 0, 0, 0, 161, 0, 0, 0, 0, 0, 0, 0, 0, 0, 0, 0, 0, 0, 0, 0, 0, 0, 0, 0, 0, 0, 0, 0, 0, 0, 0, 0, 0, 0, 0, 0, 0, 0, 0, 0, 0, 0, 0, 0, 161, 0, 0, 0, 0, 0, 0, 0, 0, 0, 0, 0, 0, 0, 0, 0, 0, 0, 0, 0, 0, 0, 0, 0, 0, 0, 0, 0, 0, 0, 0, 0, 0, 0, 0, 0, 0, 0, 0, 0, 161, 0, 0, 0, 0, 0, 0, 0, 0, 0, 0, 0, 0, 0, 0, 0, 0, 0, 0, 0, 0, 0, 0, 0, 0, 0, 0, 0, 0, 0, 0, 0, 0, 0, 0, 0, 0, 0, 0, 0, 161, 0, 0, 0, 0, 0, 0, 0, 0, 0, 0, 0, 0, 0, 0, 0, 0, 0, 0, 0, 0, 0, 0, 0, 0, 0, 0, 0, 0, 0, 0, 0, 0, 0, 0, 0, 0, 0, 0, 0, 161, 0, 0, 0, 0, 0, 0, 0, 0, 0, 0, 0, 0, 0, 0, 0, 0, 0, 0, 0, 0, 0, 0, 0, 0, 0, 0, 0, 0, 0, 0, 0, 0, 0, 0, 0, 0, 0, 0, 0, 0, 0, 0, 0, 0, 0, 0, 0, 0, 0, 0, 0, 0, 0, 0, 0, 0, 0],
         "height":25,
         "name":"tile_7",
         "opacity":1,
         "type":"tilelayer",
         "visible":false,
         "width":40,
         "x":0,
         "y":0
        }, 
        {
         "draworder":"topdown",
         "height":0,
         "name":"scene_6",
         "objects":[],
         "opacity":1,
         "properties":
            {
             "#tile":"tile_6",
             "set":"{\"_\":[\"stencil\",\"stageModel\"]}",
             "stageName":"\"Arena\"",
             "states":"{ \"name\":\"game\", \"like\":{ \"_\":[ \"stencil\", \"modelFoodKeeper\" ] } }"
            },
         "type":"objectgroup",
         "visible":false,
         "width":0,
         "x":0,
         "y":0
        }, 
        {
         "data":[0, 0, 0, 0, 0, 0, 0, 0, 0, 0, 0, 0, 0, 0, 0, 0, 0, 0, 0, 0, 0, 0, 0, 0, 0, 0, 0, 0, 0, 0, 0, 0, 0, 0, 0, 0, 0, 0, 0, 0, 161, 161, 161, 161, 161, 161, 161, 161, 161, 161, 161, 161, 161, 161, 161, 161, 161, 161, 161, 161, 161, 161, 161, 161, 161, 161, 161, 161, 161, 161, 161, 161, 161, 161, 161, 161, 161, 161, 161, 161, 161, 0, 0, 0, 0, 0, 0, 0, 0, 0, 0, 0, 0, 0, 0, 0, 0, 0, 0, 0, 0, 0, 0, 0, 0, 0, 0, 0, 0, 0, 0, 0, 0, 0, 0, 0, 0, 0, 0, 161, 161, 0, 0, 0, 0, 0, 0, 0, 0, 0, 0, 0, 0, 0, 0, 0, 0, 0, 0, 0, 0, 0, 0, 0, 0, 0, 0, 0, 0, 0, 0, 0, 0, 0, 0, 0, 0, 0, 0, 161, 161, 0, 0, 0, 0, 0, 0, 0, 0, 0, 0, 0, 0, 0, 0, 0, 0, 0, 0, 0, 0, 0, 0, 0, 0, 0, 0, 0, 161, 0, 0, 0, 0, 0, 0, 0, 0, 0, 0, 161, 161, 0, 0, 0, 0, 0, 0, 0, 0, 0, 0, 161, 0, 0, 0, 0, 0, 0, 0, 0, 0, 0, 0, 0, 0, 0, 0, 0, 161, 0, 0, 0, 0, 0, 0, 0, 0, 0, 0, 161, 161, 0, 0, 0, 0, 0, 0, 0, 0, 0, 0, 161, 0, 0, 0, 0, 0, 0, 0, 0, 0, 0, 0, 0, 0, 0, 0, 0, 161, 0, 0, 0, 0, 0, 0, 0, 0, 0, 0, 161, 161, 0, 0, 0, 0, 0, 0, 0, 0, 0, 0, 161, 0, 0, 0, 0, 0, 0, 0, 0, 0, 0, 0, 0, 0, 0, 0, 0, 161, 0, 0, 0, 0, 0, 0, 0, 0, 0, 0, 161, 161, 0, 0, 0, 0, 0, 0, 0, 0, 0, 0, 161, 0, 0, 0, 0, 0, 0, 0, 0, 0, 0, 0, 0, 0, 0, 0, 0, 161, 0, 0, 0, 0, 0, 0, 0, 0, 0, 0, 161, 161, 0, 0, 0, 0, 0, 0, 0, 0, 0, 0, 161, 0, 0, 0, 0, 0, 0, 0, 0, 0, 0, 0, 0, 0, 0, 0, 0, 161, 0, 0, 0, 0, 0, 0, 0, 0, 0, 0, 161, 161, 0, 0, 0, 0, 0, 0, 0, 0, 0, 0, 161, 0, 0, 0, 0, 0, 0, 0, 0, 0, 0, 0, 0, 0, 0, 0, 0, 161, 0, 0, 0, 0, 0, 0, 0, 0, 0, 0, 161, 0, 0, 0, 0, 0, 0, 0, 0, 0, 0, 0, 161, 0, 0, 0, 0, 0, 0, 0, 0, 0, 0, 0, 0, 0, 0, 0, 0, 161, 0, 0, 0, 0, 0, 0, 0, 0, 0, 0, 0, 0, 0, 0, 0, 0, 0, 0, 0, 0, 0, 0, 161, 0, 0, 0, 0, 0, 0, 0, 0, 0, 0, 0, 0, 0, 0, 0, 0, 161, 0, 0, 0, 0, 0, 0, 0, 0, 0, 0, 0, 0, 0, 0, 0, 0, 0, 0, 0, 0, 0, 0, 161, 0, 0, 0, 0, 0, 0, 0, 0, 0, 0, 0, 0, 0, 0, 0, 0, 161, 0, 0, 0, 0, 0, 0, 0, 0, 0, 0, 0, 161, 0, 0, 0, 0, 0, 0, 0, 0, 0, 0, 161, 0, 0, 0, 0, 0, 0, 0, 0, 0, 0, 0, 0, 0, 0, 0, 0, 161, 0, 0, 0, 0, 0, 0, 0, 0, 0, 0, 161, 161, 0, 0, 0, 0, 0, 0, 0, 0, 0, 0, 161, 0, 0, 0, 0, 0, 0, 0, 0, 0, 0, 0, 0, 0, 0, 0, 0, 161, 0, 0, 0, 0, 0, 0, 0, 0, 0, 0, 161, 161, 0, 0, 0, 0, 0, 0, 0, 0, 0, 0, 161, 0, 0, 0, 0, 0, 0, 0, 0, 0, 0, 0, 0, 0, 0, 0, 0, 161, 0, 0, 0, 0, 0, 0, 0, 0, 0, 0, 161, 161, 0, 0, 0, 0, 0, 0, 0, 0, 0, 0, 161, 0, 0, 0, 0, 0, 0, 0, 0, 0, 0, 0, 0, 0, 0, 0, 0, 161, 0, 0, 0, 0, 0, 0, 0, 0, 0, 0, 161, 161, 0, 0, 0, 0, 0, 0, 0, 0, 0, 0, 161, 0, 0, 0, 0, 0, 0, 0, 0, 0, 0, 0, 0, 0, 0, 0, 0, 161, 0, 0, 0, 0, 0, 0, 0, 0, 0, 0, 161, 161, 0, 0, 0, 0, 0, 0, 0, 0, 0, 0, 161, 0, 0, 0, 0, 0, 0, 0, 0, 0, 0, 0, 0, 0, 0, 0, 0, 161, 0, 0, 0, 0, 0, 0, 0, 0, 0, 0, 161, 161, 0, 0, 0, 0, 0, 0, 0, 0, 0, 0, 0, 0, 0, 0, 0, 0, 0, 0, 0, 0, 0, 0, 0, 0, 0, 0, 0, 161, 0, 0, 0, 0, 0, 0, 0, 0, 0, 0, 161, 161, 0, 0, 0, 0, 0, 0, 0, 0, 0, 0, 0, 0, 0, 0, 0, 0, 0, 0, 0, 0, 0, 0, 0, 0, 0, 0, 0, 0, 0, 0, 0, 0, 0, 0, 0, 0, 0, 0, 161, 161, 0, 0, 0, 0, 0, 0, 0, 0, 0, 0, 0, 0, 0, 0, 0, 0, 0, 0, 0, 0, 0, 0, 0, 0, 0, 0, 0, 0, 0, 0, 0, 0, 0, 0, 0, 0, 0, 0, 161, 161, 161, 161, 161, 161, 161, 161, 161, 161, 161, 161, 161, 161, 161, 161, 161, 161, 161, 161, 161, 161, 161, 161, 161, 161, 161, 161, 161, 161, 161, 161, 161, 161, 161, 161, 161, 161, 161, 161, 161, 0, 0, 0, 0, 0, 0, 0, 0, 0, 0, 0, 0, 0, 0, 0, 0, 0, 0, 0, 0, 0, 0, 0, 0, 0, 0, 0, 0, 0, 0, 0, 0, 0, 0, 0, 0, 0, 0, 0, 0],
         "height":25,
         "name":"tile_6",
         "opacity":1,
         "type":"tilelayer",
         "visible":false,
         "width":40,
         "x":0,
         "y":0
        }, 
        {
         "draworder":"topdown",
         "height":0,
         "name":"scene_5",
         "objects":[],
         "opacity":1,
         "properties":
            {
             "#tile":"tile_5",
             "set":"{\"_\":[\"stencil\",\"stageModel\"]}",
             "stageName":"\"Vortex\"",
             "states":"{ \"name\":\"game\", \"like\":{ \"_\":[ \"stencil\", \"modelFoodKeeper\" ] } }"
            },
         "type":"objectgroup",
         "visible":false,
         "width":0,
         "x":0,
         "y":0
        }, 
        {
         "data":[0, 0, 0, 0, 0, 0, 0, 0, 0, 0, 0, 0, 0, 0, 0, 0, 0, 0, 0, 0, 0, 0, 0, 0, 0, 0, 0, 0, 0, 0, 0, 0, 0, 0, 0, 0, 0, 0, 0, 0, 0, 0, 0, 0, 0, 0, 0, 0, 0, 0, 0, 0, 0, 0, 0, 161, 0, 0, 0, 0, 0, 0, 0, 0, 0, 0, 0, 0, 0, 0, 0, 0, 0, 0, 0, 0, 0, 0, 0, 0, 0, 0, 0, 0, 0, 0, 0, 0, 0, 0, 0, 0, 0, 0, 0, 161, 0, 0, 0, 0, 0, 0, 0, 0, 0, 0, 0, 0, 0, 0, 0, 0, 0, 0, 0, 0, 0, 0, 0, 0, 0, 0, 0, 0, 0, 0, 0, 0, 0, 0, 0, 0, 0, 0, 0, 161, 0, 0, 0, 0, 0, 0, 0, 0, 0, 0, 0, 0, 0, 0, 0, 0, 0, 0, 0, 0, 0, 0, 0, 0, 0, 0, 0, 0, 0, 0, 0, 0, 0, 0, 0, 0, 0, 0, 0, 161, 0, 0, 0, 0, 0, 0, 0, 0, 0, 0, 0, 161, 161, 161, 161, 161, 161, 161, 161, 161, 161, 161, 161, 161, 0, 0, 0, 0, 0, 0, 0, 0, 0, 0, 0, 0, 0, 0, 0, 161, 0, 0, 0, 0, 0, 0, 0, 0, 0, 0, 0, 0, 0, 0, 0, 0, 0, 0, 0, 0, 0, 0, 0, 0, 0, 0, 0, 0, 0, 0, 0, 0, 0, 0, 0, 0, 0, 0, 0, 161, 0, 0, 0, 0, 0, 0, 0, 0, 0, 0, 0, 0, 0, 0, 0, 0, 0, 0, 0, 0, 0, 0, 0, 0, 0, 0, 0, 0, 0, 0, 0, 0, 0, 0, 0, 0, 0, 0, 0, 161, 0, 0, 0, 0, 0, 0, 0, 0, 0, 0, 0, 0, 0, 0, 0, 0, 0, 0, 0, 0, 0, 0, 0, 0, 0, 0, 0, 0, 0, 0, 0, 0, 0, 0, 0, 0, 0, 0, 0, 161, 0, 0, 0, 0, 0, 0, 0, 0, 0, 0, 0, 0, 0, 0, 0, 0, 0, 0, 0, 0, 0, 0, 0, 0, 0, 0, 0, 0, 0, 0, 0, 0, 0, 0, 0, 0, 0, 0, 0, 161, 0, 0, 0, 0, 0, 0, 0, 0, 0, 0, 0, 0, 0, 0, 0, 0, 0, 0, 0, 0, 0, 0, 0, 0, 0, 0, 0, 0, 0, 0, 0, 0, 0, 0, 0, 0, 0, 0, 0, 161, 0, 0, 0, 0, 0, 0, 0, 0, 0, 0, 0, 0, 0, 0, 0, 0, 0, 0, 0, 0, 0, 0, 0, 0, 0, 0, 0, 0, 0, 0, 0, 0, 0, 0, 0, 0, 0, 0, 0, 161, 0, 0, 0, 0, 0, 0, 0, 0, 0, 0, 0, 0, 0, 0, 0, 0, 0, 0, 0, 0, 0, 0, 0, 0, 0, 0, 0, 0, 0, 0, 0, 0, 0, 0, 0, 0, 0, 0, 0, 0, 0, 0, 0, 0, 0, 0, 0, 0, 0, 0, 0, 0, 0, 0, 0, 0, 0, 0, 0, 0, 0, 0, 0, 0, 0, 0, 0, 0, 0, 0, 0, 0, 0, 0, 0, 0, 0, 0, 0, 0, 0, 0, 0, 0, 0, 0, 0, 0, 161, 0, 0, 0, 0, 0, 0, 0, 0, 0, 0, 0, 0, 0, 0, 0, 0, 0, 0, 0, 0, 0, 0, 0, 0, 0, 0, 0, 0, 0, 0, 0, 0, 0, 0, 0, 0, 0, 0, 0, 161, 0, 0, 0, 0, 0, 0, 0, 0, 0, 0, 0, 0, 0, 0, 0, 0, 0, 0, 0, 0, 0, 0, 0, 0, 0, 0, 0, 0, 0, 0, 0, 0, 0, 0, 0, 0, 0, 0, 0, 161, 0, 0, 0, 0, 0, 0, 0, 0, 0, 0, 0, 0, 0, 0, 0, 0, 0, 0, 0, 0, 0, 0, 0, 0, 0, 0, 0, 0, 0, 0, 0, 0, 0, 0, 0, 0, 0, 0, 0, 161, 0, 0, 0, 0, 0, 0, 0, 0, 0, 0, 0, 0, 0, 0, 0, 0, 0, 0, 0, 0, 0, 0, 0, 0, 0, 0, 0, 0, 0, 0, 0, 0, 0, 0, 0, 0, 0, 0, 0, 161, 0, 0, 0, 0, 0, 0, 0, 0, 0, 0, 0, 0, 0, 0, 0, 0, 0, 0, 0, 0, 0, 0, 0, 0, 0, 0, 0, 0, 0, 0, 0, 0, 0, 0, 0, 0, 0, 0, 0, 161, 0, 0, 0, 0, 0, 0, 0, 0, 0, 0, 0, 0, 0, 0, 0, 0, 0, 0, 0, 0, 0, 0, 0, 0, 0, 0, 0, 0, 0, 0, 0, 0, 0, 0, 0, 0, 0, 0, 0, 161, 0, 0, 0, 0, 0, 0, 0, 0, 0, 0, 0, 0, 0, 0, 0, 161, 161, 161, 161, 161, 161, 161, 161, 161, 161, 161, 161, 161, 0, 0, 0, 0, 0, 0, 0, 0, 0, 0, 0, 161, 0, 0, 0, 0, 0, 0, 0, 0, 0, 0, 0, 0, 0, 0, 0, 0, 0, 0, 0, 0, 0, 0, 0, 0, 0, 0, 0, 0, 0, 0, 0, 0, 0, 0, 0, 0, 0, 0, 0, 161, 0, 0, 0, 0, 0, 0, 0, 0, 0, 0, 0, 0, 0, 0, 0, 0, 0, 0, 0, 0, 0, 0, 0, 0, 0, 0, 0, 0, 0, 0, 0, 0, 0, 0, 0, 0, 0, 0, 0, 161, 0, 0, 0, 0, 0, 0, 0, 0, 0, 0, 0, 0, 0, 0, 0, 0, 0, 0, 0, 0, 0, 0, 0, 0, 0, 0, 0, 0, 0, 0, 0, 0, 0, 0, 0, 0, 0, 0, 0, 161, 0, 0, 0, 0, 0, 0, 0, 0, 0, 0, 0, 0, 0, 0, 0, 0, 0, 0, 0, 0, 0, 0, 0, 0, 0, 0, 0, 0, 0, 0, 0, 0, 0, 0, 0, 0, 0, 0, 0, 0, 0, 0, 0, 0, 0, 0, 0, 0, 0, 0, 0, 0, 0, 0, 0],
         "height":25,
         "name":"tile_5",
         "opacity":1,
         "type":"tilelayer",
         "visible":false,
         "width":40,
         "x":0,
         "y":0
        }, 
        {
         "draworder":"topdown",
         "height":0,
         "name":"scene_4",
         "objects":[],
         "opacity":1,
         "properties":
            {
             "#tile":"tile_4",
             "set":"{\"_\":[\"stencil\",\"stageModel\"]}",
             "stageName":"\"Plus Equals\"",
             "states":"{ \"name\":\"game\", \"like\":{ \"_\":[ \"stencil\", \"modelFoodKeeper\" ] } }"
            },
         "type":"objectgroup",
         "visible":false,
         "width":0,
         "x":0,
         "y":0
        }, 
        {
         "data":[0, 0, 0, 0, 0, 0, 0, 0, 0, 0, 0, 0, 0, 0, 0, 0, 0, 0, 0, 0, 0, 0, 0, 0, 0, 0, 0, 0, 0, 0, 0, 0, 0, 0, 0, 0, 0, 0, 0, 0, 161, 161, 161, 161, 161, 161, 0, 0, 0, 0, 0, 0, 0, 0, 0, 0, 0, 0, 0, 0, 0, 0, 0, 0, 0, 0, 0, 0, 0, 0, 0, 0, 0, 0, 161, 161, 161, 161, 161, 161, 161, 0, 0, 0, 0, 0, 0, 0, 0, 0, 0, 0, 0, 0, 0, 0, 0, 0, 0, 0, 0, 0, 0, 0, 0, 0, 0, 0, 0, 0, 0, 0, 0, 0, 0, 0, 0, 0, 0, 161, 161, 0, 0, 0, 0, 0, 0, 0, 0, 0, 0, 0, 0, 0, 0, 0, 0, 0, 0, 0, 0, 0, 0, 0, 0, 0, 0, 0, 0, 0, 0, 0, 0, 0, 0, 0, 0, 0, 0, 161, 161, 0, 0, 0, 0, 0, 0, 0, 0, 0, 0, 0, 0, 0, 0, 0, 0, 0, 0, 0, 0, 0, 0, 0, 0, 0, 0, 0, 0, 0, 0, 0, 0, 0, 0, 0, 0, 0, 0, 161, 161, 0, 0, 0, 0, 0, 0, 0, 0, 0, 0, 0, 0, 0, 0, 0, 0, 0, 0, 0, 0, 0, 0, 0, 0, 0, 0, 0, 0, 0, 0, 0, 0, 0, 0, 0, 0, 0, 0, 161, 161, 0, 0, 0, 0, 0, 0, 0, 0, 0, 0, 0, 0, 0, 0, 0, 0, 0, 0, 0, 0, 0, 0, 0, 0, 0, 0, 0, 0, 0, 0, 0, 0, 0, 0, 0, 0, 0, 0, 161, 0, 0, 0, 0, 0, 0, 0, 0, 0, 0, 0, 0, 0, 0, 0, 0, 0, 0, 0, 0, 0, 0, 0, 0, 0, 0, 0, 0, 0, 0, 0, 0, 0, 0, 0, 0, 0, 0, 0, 0, 0, 0, 0, 0, 0, 0, 0, 0, 0, 0, 0, 0, 0, 0, 0, 0, 0, 0, 0, 0, 0, 0, 0, 0, 0, 0, 0, 0, 0, 0, 0, 0, 0, 0, 0, 0, 0, 0, 0, 0, 0, 0, 0, 0, 0, 0, 0, 0, 0, 0, 0, 0, 0, 0, 0, 0, 0, 0, 0, 0, 0, 0, 0, 0, 0, 0, 0, 0, 0, 0, 0, 0, 0, 0, 0, 0, 0, 0, 0, 0, 0, 0, 0, 0, 0, 0, 0, 0, 0, 0, 0, 0, 0, 0, 161, 161, 161, 161, 161, 161, 161, 161, 161, 161, 161, 161, 0, 0, 0, 0, 0, 0, 0, 0, 0, 0, 0, 0, 0, 0, 0, 0, 0, 0, 0, 0, 0, 0, 0, 0, 0, 0, 0, 0, 0, 0, 0, 0, 0, 0, 0, 0, 0, 0, 0, 0, 0, 0, 0, 0, 0, 0, 0, 0, 0, 0, 0, 0, 0, 0, 0, 0, 0, 0, 0, 0, 0, 0, 0, 0, 0, 0, 0, 0, 0, 0, 0, 0, 0, 0, 0, 0, 0, 0, 0, 0, 0, 0, 0, 0, 0, 0, 0, 0, 0, 0, 0, 0, 0, 0, 0, 0, 0, 0, 0, 0, 0, 0, 0, 0, 0, 0, 0, 0, 0, 0, 0, 0, 0, 0, 0, 0, 0, 0, 0, 0, 0, 0, 0, 0, 0, 0, 0, 0, 0, 0, 0, 0, 0, 0, 0, 0, 0, 0, 0, 0, 0, 0, 0, 0, 0, 0, 0, 0, 161, 161, 161, 161, 161, 161, 161, 161, 161, 161, 161, 161, 0, 0, 0, 0, 0, 0, 0, 0, 0, 0, 0, 0, 0, 0, 0, 0, 0, 0, 0, 0, 0, 0, 0, 0, 0, 0, 0, 0, 0, 0, 0, 0, 0, 0, 0, 0, 0, 0, 0, 0, 0, 0, 0, 0, 0, 0, 0, 0, 0, 0, 0, 0, 0, 0, 0, 0, 0, 0, 0, 0, 0, 0, 0, 0, 0, 0, 0, 0, 0, 0, 0, 0, 0, 0, 0, 0, 0, 0, 0, 0, 0, 0, 0, 0, 0, 0, 0, 0, 0, 0, 0, 0, 0, 0, 0, 0, 0, 0, 0, 0, 0, 0, 0, 0, 0, 0, 0, 0, 0, 0, 0, 0, 0, 0, 0, 0, 0, 0, 0, 0, 0, 0, 0, 0, 0, 0, 0, 0, 0, 0, 0, 0, 0, 0, 161, 0, 0, 0, 0, 0, 0, 0, 0, 0, 0, 0, 0, 0, 0, 0, 0, 0, 0, 0, 0, 0, 0, 0, 0, 0, 0, 0, 0, 0, 0, 0, 0, 0, 0, 0, 0, 0, 0, 161, 161, 0, 0, 0, 0, 0, 0, 0, 0, 0, 0, 0, 0, 0, 0, 0, 0, 0, 0, 0, 0, 0, 0, 0, 0, 0, 0, 0, 0, 0, 0, 0, 0, 0, 0, 0, 0, 0, 0, 161, 161, 0, 0, 0, 0, 0, 0, 0, 0, 0, 0, 0, 0, 0, 0, 0, 0, 0, 0, 0, 0, 0, 0, 0, 0, 0, 0, 0, 0, 0, 0, 0, 0, 0, 0, 0, 0, 0, 0, 161, 161, 0, 0, 0, 0, 0, 0, 0, 0, 0, 0, 0, 0, 0, 0, 0, 0, 0, 0, 0, 0, 0, 0, 0, 0, 0, 0, 0, 0, 0, 0, 0, 0, 0, 0, 0, 0, 0, 0, 161, 161, 0, 0, 0, 0, 0, 0, 0, 0, 0, 0, 0, 0, 0, 0, 0, 0, 0, 0, 0, 0, 0, 0, 0, 0, 0, 0, 0, 0, 0, 0, 0, 0, 0, 0, 0, 0, 0, 0, 161, 161, 161, 161, 161, 161, 161, 0, 0, 0, 0, 0, 0, 0, 0, 0, 0, 0, 0, 0, 0, 0, 0, 0, 0, 0, 0, 0, 0, 0, 0, 0, 0, 0, 0, 161, 161, 161, 161, 161, 161, 0, 0, 0, 0, 0, 0, 0, 0, 0, 0, 0, 0, 0, 0, 0, 0, 0, 0, 0, 0, 0, 0, 0, 0, 0, 0, 0, 0, 0, 0, 0, 0, 0, 0, 0, 0, 0, 0, 0, 0],
         "height":25,
         "name":"tile_4",
         "opacity":1,
         "type":"tilelayer",
         "visible":false,
         "width":40,
         "x":0,
         "y":0
        }, 
        {
         "draworder":"topdown",
         "height":0,
         "name":"scene_3",
         "objects":[],
         "opacity":1,
         "properties":
            {
             "#tile":"tile_3",
             "set":"{\"_\":[\"stencil\",\"stageModel\"]}",
             "stageName":"\"Splitted\"",
             "startX":"14",
             "states":"{ \"name\":\"game\", \"like\":{ \"_\":[ \"stencil\", \"modelFoodKeeper\" ] } }"
            },
         "type":"objectgroup",
         "visible":false,
         "width":0,
         "x":0,
         "y":0
        }, 
        {
         "data":[0, 0, 0, 0, 0, 0, 0, 0, 0, 0, 0, 0, 0, 0, 0, 0, 0, 0, 0, 0, 0, 0, 0, 0, 0, 0, 0, 0, 0, 0, 0, 0, 0, 0, 0, 0, 0, 0, 0, 0, 161, 161, 161, 161, 161, 161, 161, 161, 161, 161, 161, 161, 161, 161, 161, 161, 161, 161, 161, 161, 161, 161, 161, 161, 161, 161, 161, 161, 161, 161, 161, 161, 161, 161, 161, 161, 161, 161, 161, 161, 0, 0, 0, 0, 0, 0, 0, 0, 0, 0, 0, 0, 0, 0, 0, 0, 0, 0, 0, 0, 161, 0, 0, 0, 0, 0, 0, 0, 0, 0, 0, 0, 0, 0, 0, 0, 0, 0, 0, 0, 0, 0, 0, 0, 0, 0, 0, 0, 0, 0, 0, 0, 0, 0, 0, 0, 0, 0, 0, 0, 161, 0, 0, 0, 0, 0, 0, 0, 0, 0, 0, 0, 0, 0, 0, 0, 0, 0, 0, 0, 0, 0, 0, 0, 0, 0, 0, 0, 0, 0, 0, 0, 0, 0, 0, 0, 0, 0, 0, 0, 161, 0, 0, 0, 0, 0, 0, 0, 0, 0, 0, 0, 0, 0, 0, 0, 0, 0, 0, 0, 0, 0, 0, 0, 0, 0, 0, 0, 0, 0, 0, 0, 0, 0, 0, 0, 0, 0, 0, 0, 161, 0, 0, 0, 0, 0, 0, 0, 0, 0, 0, 0, 0, 0, 0, 0, 0, 0, 0, 0, 0, 0, 0, 0, 0, 0, 0, 0, 0, 0, 0, 0, 0, 0, 0, 0, 0, 0, 0, 0, 161, 0, 0, 0, 0, 0, 0, 0, 0, 0, 0, 0, 0, 0, 0, 0, 0, 0, 0, 0, 0, 0, 0, 0, 0, 0, 0, 0, 0, 0, 0, 0, 0, 0, 0, 0, 0, 0, 0, 0, 161, 0, 0, 0, 0, 0, 0, 0, 0, 0, 0, 0, 0, 0, 0, 0, 0, 0, 0, 0, 0, 0, 0, 0, 0, 0, 0, 0, 0, 0, 0, 0, 0, 0, 0, 0, 0, 0, 0, 0, 161, 0, 0, 0, 0, 0, 0, 0, 0, 0, 0, 0, 0, 0, 0, 0, 0, 0, 0, 0, 0, 0, 0, 0, 0, 0, 0, 0, 0, 0, 0, 0, 0, 0, 0, 0, 0, 0, 0, 0, 161, 0, 0, 0, 0, 0, 0, 0, 0, 0, 0, 0, 0, 0, 0, 0, 0, 0, 0, 0, 0, 0, 0, 0, 0, 0, 0, 0, 0, 0, 0, 0, 0, 0, 0, 0, 0, 0, 0, 0, 161, 0, 0, 0, 0, 0, 0, 0, 0, 0, 0, 0, 0, 0, 0, 0, 0, 0, 0, 0, 0, 0, 0, 0, 0, 0, 0, 0, 0, 0, 0, 0, 0, 0, 0, 0, 0, 0, 0, 0, 161, 0, 0, 0, 0, 0, 0, 0, 0, 0, 0, 0, 0, 0, 0, 0, 0, 0, 0, 0, 0, 0, 0, 0, 0, 0, 0, 0, 0, 0, 0, 0, 0, 0, 0, 0, 0, 0, 0, 0, 161, 0, 0, 0, 0, 0, 0, 0, 0, 0, 0, 0, 0, 0, 0, 0, 0, 0, 0, 0, 0, 0, 0, 0, 0, 0, 0, 0, 0, 0, 0, 0, 0, 0, 0, 0, 0, 0, 0, 0, 161, 0, 0, 0, 0, 0, 0, 0, 0, 0, 0, 0, 0, 0, 0, 0, 0, 0, 0, 0, 0, 0, 0, 0, 0, 0, 0, 0, 0, 0, 0, 0, 0, 0, 0, 0, 0, 0, 0, 0, 161, 0, 0, 0, 0, 0, 0, 0, 0, 0, 0, 0, 0, 0, 0, 0, 0, 0, 0, 0, 0, 0, 0, 0, 0, 0, 0, 0, 0, 0, 0, 0, 0, 0, 0, 0, 0, 0, 0, 0, 161, 0, 0, 0, 0, 0, 0, 0, 0, 0, 0, 0, 0, 0, 0, 0, 0, 0, 0, 0, 0, 0, 0, 0, 0, 0, 0, 0, 0, 0, 0, 0, 0, 0, 0, 0, 0, 0, 0, 0, 161, 0, 0, 0, 0, 0, 0, 0, 0, 0, 0, 0, 0, 0, 0, 0, 0, 0, 0, 0, 0, 0, 0, 0, 0, 0, 0, 0, 0, 0, 0, 0, 0, 0, 0, 0, 0, 0, 0, 0, 161, 0, 0, 0, 0, 0, 0, 0, 0, 0, 0, 0, 0, 0, 0, 0, 0, 0, 0, 0, 0, 0, 0, 0, 0, 0, 0, 0, 0, 0, 0, 0, 0, 0, 0, 0, 0, 0, 0, 0, 161, 0, 0, 0, 0, 0, 0, 0, 0, 0, 0, 0, 0, 0, 0, 0, 0, 0, 0, 0, 0, 0, 0, 0, 0, 0, 0, 0, 0, 0, 0, 0, 0, 0, 0, 0, 0, 0, 0, 0, 161, 0, 0, 0, 0, 0, 0, 0, 0, 0, 0, 0, 0, 0, 0, 0, 0, 0, 0, 0, 0, 0, 0, 0, 0, 0, 0, 0, 0, 0, 0, 0, 0, 0, 0, 0, 0, 0, 0, 0, 161, 0, 0, 0, 0, 0, 0, 0, 0, 0, 0, 0, 0, 0, 0, 0, 0, 0, 0, 0, 0, 0, 0, 0, 0, 0, 0, 0, 0, 0, 0, 0, 0, 0, 0, 0, 0, 0, 0, 0, 161, 0, 0, 0, 0, 0, 0, 0, 0, 0, 0, 0, 0, 0, 0, 0, 0, 0, 0, 0, 0, 0, 0, 0, 0, 0, 0, 0, 0, 0, 0, 0, 0, 0, 0, 0, 0, 0, 0, 0, 161, 0, 0, 0, 0, 0, 0, 0, 0, 0, 0, 0, 0, 0, 0, 0, 0, 0, 0, 0, 161, 161, 161, 161, 161, 161, 161, 161, 161, 161, 161, 161, 161, 161, 161, 161, 161, 161, 161, 161, 161, 161, 161, 161, 161, 161, 161, 161, 161, 161, 161, 161, 161, 161, 161, 161, 161, 161, 161, 161, 0, 0, 0, 0, 0, 0, 0, 0, 0, 0, 0, 0, 0, 0, 0, 0, 0, 0, 0, 0, 0, 0, 0, 0, 0, 0, 0, 0, 0, 0, 0, 0, 0, 0, 0, 0, 0, 0, 0, 0],
         "height":25,
         "name":"tile_3",
         "opacity":1,
         "type":"tilelayer",
         "visible":false,
         "width":40,
         "x":0,
         "y":0
        }, 
        {
         "draworder":"topdown",
         "height":0,
         "name":"scene_2",
         "objects":[],
         "opacity":1,
         "properties":
            {
             "#tile":"tile_2",
             "set":"{\"_\":[\"stencil\",\"stageModel\"]}",
             "stageName":"\"Great wall\"",
             "states":"{ \"name\":\"game\", \"like\":{ \"_\":[ \"stencil\", \"modelFoodKeeper\" ] } }"
            },
         "type":"objectgroup",
         "visible":false,
         "width":0,
         "x":0,
         "y":0
        }, 
        {
         "data":[0, 0, 0, 0, 0, 0, 0, 0, 0, 0, 0, 0, 0, 0, 0, 0, 0, 0, 0, 0, 0, 0, 0, 0, 0, 0, 0, 0, 0, 0, 0, 0, 0, 0, 0, 0, 0, 0, 0, 0, 161, 161, 161, 161, 161, 161, 161, 161, 161, 161, 161, 161, 161, 161, 161, 161, 161, 161, 161, 161, 161, 161, 161, 161, 161, 161, 161, 161, 161, 161, 161, 161, 161, 161, 161, 161, 161, 161, 161, 161, 161, 0, 0, 0, 0, 0, 0, 0, 0, 0, 0, 0, 0, 0, 0, 0, 0, 0, 0, 0, 0, 0, 0, 0, 0, 0, 0, 0, 0, 0, 0, 0, 0, 0, 0, 0, 0, 0, 0, 161, 161, 0, 0, 0, 0, 0, 0, 0, 0, 0, 0, 0, 0, 0, 0, 0, 0, 0, 0, 0, 0, 0, 0, 0, 0, 0, 0, 0, 0, 0, 0, 0, 0, 0, 0, 0, 0, 0, 0, 161, 161, 0, 0, 0, 0, 0, 0, 0, 0, 0, 0, 0, 0, 0, 0, 0, 0, 0, 0, 0, 0, 0, 0, 0, 0, 0, 0, 0, 0, 0, 0, 0, 0, 0, 0, 0, 0, 0, 0, 161, 161, 0, 0, 0, 0, 0, 0, 0, 0, 0, 0, 0, 0, 0, 0, 0, 0, 0, 0, 0, 0, 0, 0, 0, 0, 0, 0, 0, 0, 0, 0, 0, 0, 0, 0, 0, 0, 0, 0, 161, 161, 0, 0, 0, 0, 0, 0, 0, 0, 0, 0, 0, 0, 0, 0, 0, 0, 0, 0, 0, 0, 0, 0, 0, 0, 0, 0, 0, 0, 0, 0, 0, 0, 0, 0, 0, 0, 0, 0, 161, 161, 0, 0, 0, 0, 0, 0, 0, 0, 0, 0, 0, 0, 0, 0, 0, 0, 0, 0, 0, 0, 0, 0, 0, 0, 0, 0, 0, 0, 0, 0, 0, 0, 0, 0, 0, 0, 0, 0, 161, 161, 0, 0, 0, 0, 0, 0, 0, 0, 0, 0, 0, 0, 0, 0, 0, 0, 0, 0, 0, 0, 0, 0, 0, 0, 0, 0, 0, 0, 0, 0, 0, 0, 0, 0, 0, 0, 0, 0, 161, 161, 0, 0, 0, 0, 0, 0, 0, 0, 0, 0, 0, 0, 0, 0, 0, 0, 0, 0, 0, 0, 0, 0, 0, 0, 0, 0, 0, 0, 0, 0, 0, 0, 0, 0, 0, 0, 0, 0, 161, 161, 0, 0, 0, 0, 0, 0, 0, 0, 0, 0, 0, 0, 0, 0, 0, 0, 0, 0, 0, 0, 0, 0, 0, 0, 0, 0, 0, 0, 0, 0, 0, 0, 0, 0, 0, 0, 0, 0, 161, 161, 0, 0, 0, 0, 0, 0, 0, 0, 0, 0, 0, 0, 0, 0, 0, 0, 0, 0, 0, 0, 0, 0, 0, 0, 0, 0, 0, 0, 0, 0, 0, 0, 0, 0, 0, 0, 0, 0, 161, 161, 0, 0, 0, 0, 0, 0, 0, 0, 0, 0, 0, 0, 0, 0, 0, 0, 0, 0, 0, 0, 0, 0, 0, 0, 0, 0, 0, 0, 0, 0, 0, 0, 0, 0, 0, 0, 0, 0, 161, 161, 0, 0, 0, 0, 0, 0, 0, 0, 0, 0, 0, 0, 0, 0, 0, 0, 0, 0, 0, 0, 0, 0, 0, 0, 0, 0, 0, 0, 0, 0, 0, 0, 0, 0, 0, 0, 0, 0, 161, 161, 0, 0, 0, 0, 0, 0, 0, 0, 0, 0, 0, 0, 0, 0, 0, 0, 0, 0, 0, 0, 0, 0, 0, 0, 0, 0, 0, 0, 0, 0, 0, 0, 0, 0, 0, 0, 0, 0, 161, 161, 0, 0, 0, 0, 0, 0, 0, 0, 0, 0, 0, 0, 0, 0, 0, 0, 0, 0, 0, 0, 0, 0, 0, 0, 0, 0, 0, 0, 0, 0, 0, 0, 0, 0, 0, 0, 0, 0, 161, 161, 0, 0, 0, 0, 0, 0, 0, 0, 0, 0, 0, 0, 0, 0, 0, 0, 0, 0, 0, 0, 0, 0, 0, 0, 0, 0, 0, 0, 0, 0, 0, 0, 0, 0, 0, 0, 0, 0, 161, 161, 0, 0, 0, 0, 0, 0, 0, 0, 0, 0, 0, 0, 0, 0, 0, 0, 0, 0, 0, 0, 0, 0, 0, 0, 0, 0, 0, 0, 0, 0, 0, 0, 0, 0, 0, 0, 0, 0, 161, 161, 0, 0, 0, 0, 0, 0, 0, 0, 0, 0, 0, 0, 0, 0, 0, 0, 0, 0, 0, 0, 0, 0, 0, 0, 0, 0, 0, 0, 0, 0, 0, 0, 0, 0, 0, 0, 0, 0, 161, 161, 0, 0, 0, 0, 0, 0, 0, 0, 0, 0, 0, 0, 0, 0, 0, 0, 0, 0, 0, 0, 0, 0, 0, 0, 0, 0, 0, 0, 0, 0, 0, 0, 0, 0, 0, 0, 0, 0, 161, 161, 0, 0, 0, 0, 0, 0, 0, 0, 0, 0, 0, 0, 0, 0, 0, 0, 0, 0, 0, 0, 0, 0, 0, 0, 0, 0, 0, 0, 0, 0, 0, 0, 0, 0, 0, 0, 0, 0, 161, 161, 0, 0, 0, 0, 0, 0, 0, 0, 0, 0, 0, 0, 0, 0, 0, 0, 0, 0, 0, 0, 0, 0, 0, 0, 0, 0, 0, 0, 0, 0, 0, 0, 0, 0, 0, 0, 0, 0, 161, 161, 0, 0, 0, 0, 0, 0, 0, 0, 0, 0, 0, 0, 0, 0, 0, 0, 0, 0, 0, 0, 0, 0, 0, 0, 0, 0, 0, 0, 0, 0, 0, 0, 0, 0, 0, 0, 0, 0, 161, 161, 161, 161, 161, 161, 161, 161, 161, 161, 161, 161, 161, 161, 161, 161, 161, 161, 161, 161, 161, 161, 161, 161, 161, 161, 161, 161, 161, 161, 161, 161, 161, 161, 161, 161, 161, 161, 161, 161, 161, 0, 0, 0, 0, 0, 0, 0, 0, 0, 0, 0, 0, 0, 0, 0, 0, 0, 0, 0, 0, 0, 0, 0, 0, 0, 0, 0, 0, 0, 0, 0, 0, 0, 0, 0, 0, 0, 0, 0, 0],
         "height":25,
         "name":"tile_2",
         "opacity":1,
         "type":"tilelayer",
         "visible":false,
         "width":40,
         "x":0,
         "y":0
        }, 
        {
         "draworder":"topdown",
         "height":0,
         "name":"scene_1",
         "objects":[],
         "opacity":1,
         "properties":
            {
             "set":"{\"_\":[\"stencil\",\"stageModel\"]}",
             "stageName":"\"No boundaries\"",
             "states":"{ \"name\":\"game\", \"like\":{ \"_\":[ \"stencil\", \"modelFoodKeeper\" ] } }"
            },
         "type":"objectgroup",
         "visible":false,
         "width":0,
         "x":0,
         "y":0
        }],
 "orientation":"orthogonal",
 "properties":
    {

    },
 "renderorder":"right-down",
 "tileheight":8,
 "tilesets":[
        {
         "firstgid":1,
         "image":"..\/..\/tapes\/serpents\/sprites.png",
         "imageheight":400,
         "imagewidth":640,
         "margin":0,
         "name":"sprites",
         "properties":
            {

            },
         "spacing":0,
         "tileheight":8,
         "tileproperties":
            {
             "160":
                {
                 "#stencil":"A"
                },
             "161":
                {
                 "#stencil":"B"
                },
             "162":
                {
                 "#stencil":"C"
                },
             "163":
                {
                 "#stencil":"D"
                },
             "164":
                {
                 "#stencil":"E"
                },
             "165":
                {
                 "#stencil":"F"
                },
             "166":
                {
                 "#stencil":"G"
                },
             "167":
                {
                 "#stencil":"H"
                },
             "168":
                {
                 "#stencil":"I"
                },
             "169":
                {
                 "#stencil":"J"
                },
             "170":
                {
                 "#stencil":"K"
                },
             "171":
                {
                 "#stencil":"L"
                },
             "172":
                {
                 "#stencil":"M"
                },
             "173":
                {
                 "#stencil":"N"
                },
             "174":
                {
                 "#stencil":"O"
                },
             "175":
                {
                 "#stencil":"1"
                },
             "176":
                {
                 "#stencil":"2"
                },
             "177":
                {
                 "#stencil":"3"
                },
             "179":
                {
                 "#stencil":"4"
                },
             "180":
                {
                 "#stencil":"5"
                },
             "181":
                {
                 "#stencil":"6"
                },
             "182":
                {
                 "#stencil":"7"
                },
             "183":
                {
                 "#stencil":"P"
                },
             "184":
                {
                 "#stencil":"8"
                },
             "185":
                {
                 "#stencil":"Q"
                }
            },
         "tilewidth":8
        }],
 "tilewidth":8,
 "version":1,
 "width":40
}