{
  "object":[
  	{"image":"theconquest","zIndex":10000,"width":121,"height":288,"x":348,"y":244},
    { "set":{ "_":[ "stencil", "crowd" ] }, "width":16, "height":16, "x":16, "y":768 },
    { "set":{ "_":[ "stencil", "crowd" ] }, "width":16, "height":16, "x":32, "y":752 },
    { "set":{ "_":[ "stencil", "crowd" ] }, "width":16, "height":16, "x":16, "y":384 },
    { "set":{ "_":[ "stencil", "crowd" ] }, "width":16, "height":16, "x":32, "y":384 },
    { "set":{ "_":[ "stencil", "crowd" ] }, "width":16, "height":16, "x":16, "y":16 },
    { "set":{ "_":[ "stencil", "crowd" ] }, "width":16, "height":16, "x":32, "y":32 },
    { "set":{ "_":[ "stencil", "crowd" ] }, "width":16, "height":16, "x":384, "y":16 },
    { "set":{ "_":[ "stencil", "crowd" ] }, "width":16, "height":16, "x":400, "y":32 },
    { "set":{ "_":[ "stencil", "crowd" ] }, "width":16, "height":16, "x":768, "y":16 },
    { "set":{ "_":[ "stencil", "crowd" ] }, "width":16, "height":16, "x":752, "y":32 },
    { "set":{ "_":[ "stencil", "crowd" ] }, "width":16, "height":16, "x":752, "y":384 },
    { "set":{ "_":[ "stencil", "crowd" ] }, "width":16, "height":16, "x":768, "y":384 },
    { "set":{ "_":[ "stencil", "crowd" ] }, "width":16, "height":16, "x":768, "y":768 },
    { "set":{ "_":[ "stencil", "crowd" ] }, "width":16, "height":16, "x":752, "y":752 },
    { "set":{ "_":[ "stencil", "crowd" ] }, "width":16, "height":16, "x":384, "y":752 },
    { "set":{ "_":[ "stencil", "crowd" ] }, "width":16, "height":16, "x":400, "y":768 },
    { "set":{ "_":[ "stencil", "crowd" ] }, "width":16, "height":16, "x":432, "y":704 },
    { "set":{ "_":[ "stencil", "crowd" ] }, "width":16, "height":16, "x":560, "y":736 },
    { "set":{ "_":[ "stencil", "crowd" ] }, "width":16, "height":16, "x":640, "y":704 },
    { "set":{ "_":[ "stencil", "crowd" ] }, "width":16, "height":16, "x":736, "y":656 },
    { "set":{ "_":[ "stencil", "crowd" ] }, "width":16, "height":16, "x":720, "y":496 },
    { "set":{ "_":[ "stencil", "crowd" ] }, "width":16, "height":16, "x":720, "y":304 },
    { "set":{ "_":[ "stencil", "crowd" ] }, "width":16, "height":16, "x":736, "y":160 },
    { "set":{ "_":[ "stencil", "crowd" ] }, "width":16, "height":16, "x":608, "y":64 },
    { "set":{ "_":[ "stencil", "crowd" ] }, "width":16, "height":16, "x":448, "y":64 },
    { "set":{ "_":[ "stencil", "crowd" ] }, "width":16, "height":16, "x":320, "y":64 },
    { "set":{ "_":[ "stencil", "crowd" ] }, "width":16, "height":16, "x":208, "y":80 },
    { "set":{ "_":[ "stencil", "crowd" ] }, "width":16, "height":16, "x":80, "y":64 },
    { "set":{ "_":[ "stencil", "crowd" ] }, "width":16, "height":16, "x":48, "y":176 },
    { "set":{ "_":[ "stencil", "crowd" ] }, "width":16, "height":16, "x":64, "y":288 },
    { "set":{ "_":[ "stencil", "crowd" ] }, "width":16, "height":16, "x":48, "y":464 },
    { "set":{ "_":[ "stencil", "crowd" ] }, "width":16, "height":16, "x":64, "y":592 },
    { "set":{ "_":[ "stencil", "crowd" ] }, "width":16, "height":16, "x":64, "y":720 },
    { "set":{ "_":[ "stencil", "crowd" ] }, "width":16, "height":16, "x":240, "y":704 },
    {
      "type":[ "restaurantDirection", "govpalaceDirection" ],
      "set":{ "_":[ "stencil", "warp" ] },
      "width":780, "height":10,
      "x":10, "y":0,
      "headsSide":"up",
      "headsTo":"govpalace"
    },
    { "type":"floor1", "width":800, "height":16, "x":0, "y":784 },
    {
      "type":[ "htpalaceDirection", "musicDirection", "barzoneDirection" ],
      "set":{ "_":[ "stencil", "warp" ] },
      "width":10, "height":774,
      "x":790, "y":10,
      "headsSide":"right",
      "headsTo":"barzone"
    },
    {
      "type":[ "archiveDirection", "borderDirection", "whiteironDirection" ],
      "set":{ "_":[ "stencil", "warp" ] },
      "width":10, "height":774,
      "x":0, "y":10,
      "headsSide":"left",
      "headsTo":"whiteiron"
    }
  ],
  "set":{ "_":[ "stencil", "modelStage" ] },
  "crowdCount":20,
  "darkColor":"#007f7f",
  "lightColor":"#00ffff",
  "sceneName":"La Plaza",
  "tilemap":{
    "tileWidth":16,
    "tileHeight":16,
    "map":[
      "..................................................",
      "..................................................",
      "..................................................",
      "........................MO........................",
      "........................PR........................",
      "........................PR........................",
      "........................PR........................",
      "......MNNNNNNNNNNNNNNNNNQQNNNNNNNNNNNNNNNNNO......",
      "......PQQQQQQQQQQQQQQQQQQQQQQQQQQQQQQQQQQQQR......",
      "......PQTTTTTTTTTTTTTTTTTTTTTTTTTTTTTTTTTTQR......",
      "......PR...............Z..................PR......",
      "......PR........ZZ..Z.......ZZ............PR......",
      "......PR........ZZ..Z.......ZZ............PR......",
      "......PR........ZZ.....Z..................PR......",
      "......PR....MNNNNNNNNNNNNNNNNNNNNNNNNO....PR......",
      "......PRZ..ZPQQQQQQQQQQQQQQQQQQQQQQQQR....PR......",
      "......PR....PQTTTTTTTTTTTTTTTTTTTTTTQR....PR......",
      "......PR....PR......................PR....PR......",
      "......PR.ZZ.PR......................PR....PR......",
      "......PR....PR......................PR....SU......",
      "......PR....PR......................PR............",
      "......PR....PR....MNNNNNNNNNNNNO....PR............",
      "......PR....PR....PQQQQQQQQQQQQR....PR....MO......",
      "...MNNQQNNNNQQNNNNQQTTTTTTTTTTQQNNNNQQO..MQQNNO...",
      "...PQQQQQQQQQQQQQQQR..........PQQQQQQQR..PQQQQR...",
      "...STTQQTTTTQQTTTTQR..........PQTTTTQQU..SQQTTU...",
      "......PR....PR....PQNNNNNNNNNNQR....SU....PR......",
      "......PR....PR....PQQQQQQQQQQQQR..........PR......",
      "......PR....PR....STTTTTQQTTTTTU..........PR......",
      "......PR....PR..........SU..........MO....PR......",
      "......PR.ZZ.PR......................PR....PR......",
      "......PR.ZZ.PR......................PR....PR......",
      "......PR.ZZ.PR..........MO..........PR....PR......",
      "......PR.ZZ.PQNNNNNNNNNNQQNNNNNNNNNNQR....PR......",
      "......PR.ZZ.PQQQQQQQQQQQQQQQQQQQQQQQQR....PR......",
      "......PR.ZZ.STTTTTTTTTTTQQTTTTTTTTTTTU....PR......",
      "......PR................SU................PR......",
      "......PR..................................PR......",
      "......PR..................................PR......",
      "......PR................MO................PR......",
      "......PQNNNNNNNNNNNNNNNNQQNNNNNNNNNNNNNNNNQR......",
      "......PQQQQQQQQQQQQQQQQQQQQQQQQQQQQQQQQQQQQR......",
      "......STTTTTTTTTTTTTTTTTQQTTTTTTTTTTTTTTTTTU......",
      "........................PR........................",
      "........................PR........................",
      "........................SU........................",
      "........................mn........................",
      "..................................................",
      "..................................................",
      "bbbbbbbbbbbbbbbbbbbbbbbbbbbbbbbbbbbbbbbbbbbbbbbbbb"
    ]
  }
}
